[{"status": "ACT", "competitorId": "367462", "countryShortCode": "", "weight": "70 kg", "firstName": "Diego", "profession": "0", "lastName": "Bernardes", "age": "27", "regionId": "27", "regionalCode": "0", "bibId": "", "profilePicS3key": "pukie.png", "scores": [{"score": "13780000", "scoreDisplay": "378 reps"}], "affiliateName": "Pulsar CrossFit", "affiliateId": "11246", "competitorName": "Diego Bernardes", "teamCaptain": "0", "gender": "M", "divisionId": "1", "height": "170 cm", "regionName": "South America"}, {"status": "ACT", "competitorId": "996975", "countryShortCode": "", "weight": "72 kg", "firstName": "Higor", "profession": "0", "lastName": "Alves", "age": "31", "regionId": "27", "regionalCode": "0", "bibId": "", "profilePicS3key": "dd87b-P996975_1-184.jpg", "scores": [{"score": "13600000", "scoreDisplay": "360 reps"}], "affiliateName": "CrossFit OnzeOnze", "affiliateId": "16711", "competitorName": "Higor Alves", "teamCaptain": "0", "gender": "M", "divisionId": "1", "height": "168 cm", "regionName": "South America"}, {"status": "ACT", "competitorId": "305256", "countryShortCode": "", "weight": "152 lb", "firstName": "Atila", "profession": "0", "lastName": "Cosenza", "age": "27", "regionId": "27", "regionalCode": "0", "bibId": "", "profilePicS3key": "dc8ce-P305256_3-184.jpg", "scores": [{"score": "13470000", "scoreDisplay": "347 reps"}], "affiliateName": "Pulsar CrossFit", "affiliateId": "11246", "competitorName": "Atila Cosenza", "teamCaptain": "0", "gender": "M", "divisionId": "1", "height": "", "regionName": "South America"}, {"status": "ACT", "competitorId": "422629", "countryShortCode": "", "weight": "79 kg", "firstName": "Tiago", "profession": "0", "lastName": "Groba", "age": "34", "regionId": "27", "regionalCode": "0", "bibId": "", "profilePicS3key": "b0af8-P422629_3-184.jpg", "scores": [{"score": "13390000", "scoreDisplay": "339 reps"}], "affiliateName": "CrossFit SSA", "affiliateId": "13482", "competitorName": "Tiago Groba", "teamCaptain": "0", "gender": "M", "divisionId": "1", "height": "", "regionName": "South America"}, {"status": "ACT", "competitorId": "543263", "countryShortCode": "", "weight": "187 lb", "firstName": "Victor", "profession": "0", "lastName": "Bahia", "age": "29", "regionId": "27", "regionalCode": "0", "bibId": "", "profilePicS3key": "1ce3a-P543263_1-184.jpg", "scores": [{"score": "13390000", "scoreDisplay": "339 reps"}], "affiliateName": "Pulsar CrossFit", "affiliateId": "11246", "competitorName": "Victor Bahia", "teamCaptain": "0", "gender": "M", "divisionId": "1", "height": "187 cm", "regionName": "South America"}, {"status": "ACT", "competitorId": "749620", "countryShortCode": "", "weight": "85 kg", "firstName": "Guto", "profession": "0", "lastName": "Meirelles", "age": "24", "regionId": "27", "regionalCode": "0", "bibId": "", "profilePicS3key": "2ea4c-P749620_2-184.jpg", "scores": [{"score": "13380000", "scoreDisplay": "338 reps"}], "affiliateName": "Go Piat\u00e3 CrossFit", "affiliateId": "20153", "competitorName": "Guto Meirelles", "teamCaptain": "0", "gender": "M", "divisionId": "1", "height": "176 cm", "regionName": "South America"}, {"status": "ACT", "competitorId": "123879", "countryShortCode": "", "weight": "80 kg", "firstName": "F\u00e1bio", "profession": "0", "lastName": "Ferreira", "age": "32", "regionId": "27", "regionalCode": "0", "bibId": "", "profilePicS3key": "7d0ea-P123879_1-184.jpg", "scores": [{"score": "13380000", "scoreDisplay": "338 reps"}], "affiliateName": "CrossFit Jequie", "affiliateId": "7442", "competitorName": "F\u00e1bio Ferreira", "teamCaptain": "0", "gender": "M", "divisionId": "1", "height": "183 cm", "regionName": "South America"}, {"status": "ACT", "competitorId": "775427", "countryShortCode": "", "weight": "", "firstName": "Agnaldo", "profession": "0", "lastName": "Santos", "age": "30", "regionId": "27", "regionalCode": "0", "bibId": "", "profilePicS3key": "b89dc-P775427_1-184.jpg", "scores": [{"score": "13360000", "scoreDisplay": "336 reps"}], "affiliateName": "Garagem 164 CrossFit", "affiliateId": "17676", "competitorName": "Agnaldo Santos", "teamCaptain": "0", "gender": "M", "divisionId": "1", "height": "", "regionName": "South America"}, {"status": "ACT", "competitorId": "627973", "countryShortCode": "", "weight": "83 kg", "firstName": "Igor", "profession": "0", "lastName": "Tupinamba", "age": "28", "regionId": "27", "regionalCode": "0", "bibId": "", "profilePicS3key": "9f070-P627973_2-184.jpg", "scores": [{"score": "13360000", "scoreDisplay": "336 reps"}], "affiliateName": "Pulsar CrossFit", "affiliateId": "11246", "competitorName": "Igor Tupinamba", "teamCaptain": "0", "gender": "M", "divisionId": "1", "height": "188 cm", "regionName": "South America"}, {"status": "ACT", "competitorId": "587104", "countryShortCode": "", "weight": "175 lb", "firstName": "Filipe", "profession": "0", "lastName": "Magnavita Araujo", "age": "29", "regionId": "27", "regionalCode": "0", "bibId": "", "profilePicS3key": "04d72-P587104_1-184.jpg", "scores": [{"score": "13350000", "scoreDisplay": "335 reps"}], "affiliateName": "CrossFit Alcateia", "affiliateId": "12275", "competitorName": "Filipe Magnavita Araujo", "teamCaptain": "0", "gender": "M", "divisionId": "1", "height": "180 cm", "regionName": "South America"}, {"status": "ACT", "competitorId": "759267", "countryShortCode": "", "weight": "80 kg", "firstName": "Cau\u00ea", "profession": "0", "lastName": "Lobo", "age": "27", "regionId": "27", "regionalCode": "0", "bibId": "", "profilePicS3key": "9948a-P759267_3-184.jpg", "scores": [{"score": "13310000", "scoreDisplay": "331 reps"}], "affiliateName": "Aldeia CrossFit", "affiliateId": "10632", "competitorName": "Cau\u00ea Lobo", "teamCaptain": "0", "gender": "M", "divisionId": "1", "height": "175 cm", "regionName": "South America"}, {"status": "ACT", "competitorId": "1389993", "countryShortCode": "", "weight": "82 kg", "firstName": "Luiz Daniel", "profession": "0", "lastName": "Sales", "age": "30", "regionId": "27", "regionalCode": "0", "bibId": "", "profilePicS3key": "607ab-P1389993_2-184.jpg", "scores": [{"score": "13290000", "scoreDisplay": "329 reps"}], "affiliateName": "Summer CrossFit", "affiliateId": "15017", "competitorName": "Luiz Daniel Sales", "teamCaptain": "0", "gender": "M", "divisionId": "1", "height": "2 cm", "regionName": "South America"}, {"status": "ACT", "competitorId": "1350519", "countryShortCode": "", "weight": "", "firstName": "Kinsley", "profession": "0", "lastName": "Correia", "age": "26", "regionId": "27", "regionalCode": "0", "bibId": "", "profilePicS3key": "9a814-P1350519_1-184.jpg", "scores": [{"score": "13280000", "scoreDisplay": "328 reps"}], "affiliateName": "Pulsar CrossFit", "affiliateId": "11246", "competitorName": "Kinsley Correia", "teamCaptain": "0", "gender": "M", "divisionId": "1", "height": "", "regionName": "South America"}, {"status": "ACT", "competitorId": "1061901", "countryShortCode": "", "weight": "82 kg", "firstName": "Guilherme", "profession": "0", "lastName": "Santos", "age": "32", "regionId": "27", "regionalCode": "0", "bibId": "", "profilePicS3key": "pukie.png", "scores": [{"score": "13270000", "scoreDisplay": "327 reps"}], "affiliateName": "CrossFit Alcateia", "affiliateId": "12275", "competitorName": "Guilherme Santos", "teamCaptain": "0", "gender": "M", "divisionId": "1", "height": "", "regionName": "South America"}, {"status": "ACT", "competitorId": "421250", "countryShortCode": "", "weight": "85 kg", "firstName": "Mauricio", "profession": "0", "lastName": "Mota", "age": "39", "regionId": "27", "regionalCode": "0", "bibId": "", "profilePicS3key": "7f154-P421250_1-184.jpg", "scores": [{"score": "13200000", "scoreDisplay": "320 reps"}], "affiliateName": "Garagem 164 CrossFit", "affiliateId": "17676", "competitorName": "Mauricio Mota", "teamCaptain": "0", "gender": "M", "divisionId": "18", "height": "176 cm", "regionName": "South America"}, {"status": "ACT", "competitorId": "714743", "countryShortCode": "", "weight": "74 kg", "firstName": "Duillio", "profession": "0", "lastName": "Menezes", "age": "34", "regionId": "27", "regionalCode": "0", "bibId": "", "profilePicS3key": "b62d8-P714743_1-184.jpg", "scores": [{"score": "13200000", "scoreDisplay": "320 reps"}], "affiliateName": "Pulsar CrossFit", "affiliateId": "11246", "competitorName": "Duillio Menezes", "teamCaptain": "0", "gender": "M", "divisionId": "1", "height": "174 cm", "regionName": "South America"}, {"status": "ACT", "competitorId": "1239490", "countryShortCode": "", "weight": "88 kg", "firstName": "Vinicius", "profession": "0", "lastName": "Lima", "age": "27", "regionId": "27", "regionalCode": "0", "bibId": "", "profilePicS3key": "0bab1-P1239490_1-184.jpg", "scores": [{"score": "13200000", "scoreDisplay": "320 reps"}], "affiliateName": "Aldeia CrossFit", "affiliateId": "10632", "competitorName": "Vinicius Lima", "teamCaptain": "0", "gender": "M", "divisionId": "1", "height": "", "regionName": "South America"}, {"status": "ACT", "competitorId": "909127", "countryShortCode": "", "weight": "211 lb", "firstName": "Junior", "profession": "128", "lastName": "Factum", "age": "25", "regionId": "27", "regionalCode": "0", "bibId": "", "profilePicS3key": "50e69-P909127_1-184.jpg", "scores": [{"score": "13120000", "scoreDisplay": "312 reps"}], "affiliateName": "Aldeia CrossFit", "affiliateId": "10632", "competitorName": "Junior Factum", "teamCaptain": "0", "gender": "M", "divisionId": "1", "height": "187 cm", "regionName": "South America"}, {"status": "ACT", "competitorId": "1227119", "countryShortCode": "", "weight": "74 kg", "firstName": "Marcel", "profession": "0", "lastName": "Mansur", "age": "33", "regionId": "27", "regionalCode": "0", "bibId": "", "profilePicS3key": "pukie.png", "scores": [{"score": "13110000", "scoreDisplay": "311 reps"}], "affiliateName": "CrossFit Alcateia", "affiliateId": "12275", "competitorName": "Marcel Mansur", "teamCaptain": "0", "gender": "M", "divisionId": "1", "height": "169 cm", "regionName": "South America"}, {"status": "ACT", "competitorId": "1348450", "countryShortCode": "", "weight": "83 kg", "firstName": "Honorino", "profession": "256", "lastName": "Neto", "age": "33", "regionId": "27", "regionalCode": "0", "bibId": "", "profilePicS3key": "aced4-P1348450_1-184.jpg", "scores": [{"score": "13100000", "scoreDisplay": "310 reps"}], "affiliateName": "Aldeia CrossFit", "affiliateId": "10632", "competitorName": "Honorino Neto", "teamCaptain": "0", "gender": "M", "divisionId": "1", "height": "173 cm", "regionName": "South America"}, {"status": "ACT", "competitorId": "990957", "countryShortCode": "", "weight": "", "firstName": "Daniel", "profession": "0", "lastName": "Jorge Da Silva Monteiro De Freit", "age": "28", "regionId": "27", "regionalCode": "0", "bibId": "", "profilePicS3key": "pukie.png", "scores": [{"score": "13090000", "scoreDisplay": "309 reps"}], "affiliateName": "CrossFit Alcateia", "affiliateId": "12275", "competitorName": "Daniel Jorge Da Silva Monteiro De Freit", "teamCaptain": "0", "gender": "M", "divisionId": "1", "height": "", "regionName": "South America"}, {"status": "ACT", "competitorId": "661283", "countryShortCode": "", "weight": "75 kg", "firstName": "Jose", "profession": "256", "lastName": "Maria", "age": "31", "regionId": "27", "regionalCode": "0", "bibId": "", "profilePicS3key": "ea8f9-P661283_2-184.jpg", "scores": [{"score": "13080000", "scoreDisplay": "308 reps"}], "affiliateName": "CrossFit SSA", "affiliateId": "13482", "competitorName": "Jose Maria", "teamCaptain": "0", "gender": "M", "divisionId": "1", "height": "", "regionName": "South America"}, {"status": "ACT", "competitorId": "1241119", "countryShortCode": "", "weight": "", "firstName": "Daniel", "profession": "0", "lastName": "Viana", "age": "23", "regionId": "27", "regionalCode": "0", "bibId": "", "profilePicS3key": "pukie.png", "scores": [{"score": "13060000", "scoreDisplay": "306 reps"}], "affiliateName": "Summer CrossFit", "affiliateId": "15017", "competitorName": "Daniel Viana", "teamCaptain": "0", "gender": "M", "divisionId": "1", "height": "", "regionName": "South America"}, {"status": "ACT", "competitorId": "518152", "countryShortCode": "", "weight": "90 kg", "firstName": "Pedro", "profession": "0", "lastName": "Bamberg", "age": "30", "regionId": "27", "regionalCode": "0", "bibId": "", "profilePicS3key": "pukie.png", "scores": [{"score": "13060000", "scoreDisplay": "306 reps"}], "affiliateName": "Pulsar CrossFit", "affiliateId": "11246", "competitorName": "Pedro Bamberg", "teamCaptain": "0", "gender": "M", "divisionId": "1", "height": "184 cm", "regionName": "South America"}, {"status": "ACT", "competitorId": "959068", "countryShortCode": "", "weight": "68 kg", "firstName": "Massusinei", "profession": "0", "lastName": "Silva", "age": "47", "regionId": "27", "regionalCode": "0", "bibId": "", "profilePicS3key": "95b29-P959068_1-184.jpg", "scores": [{"score": "13050000", "scoreDisplay": "305 reps"}], "affiliateName": "CrossFit OnzeOnze", "affiliateId": "16711", "competitorName": "Massusinei Silva", "teamCaptain": "0", "gender": "M", "divisionId": "3", "height": "169 cm", "regionName": "South America"}, {"status": "ACT", "competitorId": "867347", "countryShortCode": "", "weight": "79 kg", "firstName": "Eduardo", "profession": "0", "lastName": "dos Santos", "age": "36", "regionId": "27", "regionalCode": "0", "bibId": "", "profilePicS3key": "eb040-P867347_4-184.jpg", "scores": [{"score": "13050000", "scoreDisplay": "305 reps"}], "affiliateName": "CrossFit Maral", "affiliateId": "16225", "competitorName": "Eduardo dos Santos", "teamCaptain": "0", "gender": "M", "divisionId": "18", "height": "167 cm", "regionName": "South America"}, {"status": "ACT", "competitorId": "686418", "countryShortCode": "", "weight": "77 kg", "firstName": "Felipe", "profession": "128", "lastName": "d'El-Rei", "age": "22", "regionId": "27", "regionalCode": "0", "bibId": "", "profilePicS3key": "533cb-P686418_2-184.jpg", "scores": [{"score": "13040000", "scoreDisplay": "304 reps"}], "affiliateName": "CrossFit Barra Action", "affiliateId": "8031", "competitorName": "Felipe d'El-Rei", "teamCaptain": "0", "gender": "M", "divisionId": "1", "height": "175 cm", "regionName": "South America"}, {"status": "ACT", "competitorId": "406818", "countryShortCode": "", "weight": "68 kg", "firstName": "Osmar", "profession": "256", "lastName": "Neto", "age": "36", "regionId": "27", "regionalCode": "0", "bibId": "", "profilePicS3key": "3e003-P406818_7-184.jpg", "scores": [{"score": "13030000", "scoreDisplay": "303 reps"}], "affiliateName": "CrossFit 7373", "affiliateId": "18390", "competitorName": "Osmar Neto", "teamCaptain": "0", "gender": "M", "divisionId": "18", "height": "165 cm", "regionName": "South America"}, {"status": "ACT", "competitorId": "1339231", "countryShortCode": "", "weight": "", "firstName": "Bartolomeu", "profession": "0", "lastName": "Junior", "age": "31", "regionId": "27", "regionalCode": "0", "bibId": "", "profilePicS3key": "6f997-P1339231_1-184.jpg", "scores": [{"score": "13030000", "scoreDisplay": "303 reps"}], "affiliateName": "CrossFit 7373", "affiliateId": "18390", "competitorName": "Bartolomeu Junior", "teamCaptain": "0", "gender": "M", "divisionId": "1", "height": "179 cm", "regionName": "South America"}, {"status": "ACT", "competitorId": "1215811", "countryShortCode": "", "weight": "90 kg", "firstName": "Julio", "profession": "256", "lastName": "Lima", "age": "38", "regionId": "27", "regionalCode": "0", "bibId": "", "profilePicS3key": "29967-P1215811_2-184.jpg", "scores": [{"score": "13030000", "scoreDisplay": "303 reps"}], "affiliateName": "CrossFit Alcateia", "affiliateId": "12275", "competitorName": "Julio Lima", "teamCaptain": "0", "gender": "M", "divisionId": "18", "height": "180 cm", "regionName": "South America"}, {"status": "ACT", "competitorId": "1355067", "countryShortCode": "", "weight": "", "firstName": "Ari", "profession": "0", "lastName": "Junior", "age": "29", "regionId": "27", "regionalCode": "0", "bibId": "", "profilePicS3key": "pukie.png", "scores": [{"score": "13030000", "scoreDisplay": "303 reps"}], "affiliateName": "Pulsar CrossFit", "affiliateId": "11246", "competitorName": "Ari Junior", "teamCaptain": "0", "gender": "M", "divisionId": "1", "height": "", "regionName": "South America"}, {"status": "ACT", "competitorId": "927897", "countryShortCode": "", "weight": "80 kg", "firstName": "Lucas", "profession": "0", "lastName": "Viana", "age": "23", "regionId": "27", "regionalCode": "0", "bibId": "", "profilePicS3key": "bc8b5-P927897_1-184.jpg", "scores": [{"score": "13010000", "scoreDisplay": "301 reps"}], "affiliateName": "CrossFit OnzeOnze", "affiliateId": "16711", "competitorName": "Lucas Viana", "teamCaptain": "0", "gender": "M", "divisionId": "1", "height": "173 cm", "regionName": "South America"}, {"status": "ACT", "competitorId": "1235016", "countryShortCode": "", "weight": "87 kg", "firstName": "Erlan", "profession": "256", "lastName": "Uz\u00eada", "age": "26", "regionId": "27", "regionalCode": "0", "bibId": "", "profilePicS3key": "pukie.png", "scores": [{"score": "13010000", "scoreDisplay": "301 reps"}], "affiliateName": "CrossFit Maral", "affiliateId": "16225", "competitorName": "Erlan Uz\u00eada", "teamCaptain": "0", "gender": "M", "divisionId": "1", "height": "177 cm", "regionName": "South America"}, {"status": "ACT", "competitorId": "606107", "countryShortCode": "", "weight": "75 kg", "firstName": "Diego", "profession": "0", "lastName": "Matos", "age": "32", "regionId": "27", "regionalCode": "0", "bibId": "", "profilePicS3key": "c7fa6-P606107_2-184.jpg", "scores": [{"score": "13010000", "scoreDisplay": "301 reps"}], "affiliateName": "Pulsar CrossFit", "affiliateId": "11246", "competitorName": "Diego Matos", "teamCaptain": "0", "gender": "M", "divisionId": "1", "height": "175 cm", "regionName": "South America"}, {"status": "ACT", "competitorId": "1205847", "countryShortCode": "", "weight": "", "firstName": "Joao", "profession": "0", "lastName": "Oliveira De Souza Junior", "age": "24", "regionId": "27", "regionalCode": "0", "bibId": "", "profilePicS3key": "pukie.png", "scores": [{"score": "13000000", "scoreDisplay": "300 reps"}], "affiliateName": "CrossFit 7373", "affiliateId": "18390", "competitorName": "Joao Oliveira De Souza Junior", "teamCaptain": "0", "gender": "M", "divisionId": "1", "height": "", "regionName": "South America"}, {"status": "ACT", "competitorId": "811794", "countryShortCode": "", "weight": "", "firstName": "Kilson", "profession": "0", "lastName": "Santana", "age": "25", "regionId": "27", "regionalCode": "0", "bibId": "", "profilePicS3key": "4db2d-P811794_3-184.jpg", "scores": [{"score": "13000000", "scoreDisplay": "300 reps"}], "affiliateName": "CrossFit Barra Action", "affiliateId": "8031", "competitorName": "Kilson Santana", "teamCaptain": "0", "gender": "M", "divisionId": "1", "height": "", "regionName": "South America"}, {"status": "ACT", "competitorId": "553825", "countryShortCode": "", "weight": "180 lb", "firstName": "Ricardo", "profession": "0", "lastName": "Leahy", "age": "24", "regionId": "27", "regionalCode": "0", "bibId": "", "profilePicS3key": "597e4-P553825_2-184.jpg", "scores": [{"score": "12980000", "scoreDisplay": "298 reps"}], "affiliateName": "Pulsar CrossFit", "affiliateId": "11246", "competitorName": "Ricardo Leahy", "teamCaptain": "0", "gender": "M", "divisionId": "1", "height": "177 cm", "regionName": "South America"}, {"status": "ACT", "competitorId": "1369270", "countryShortCode": "", "weight": "88 kg", "firstName": "Ricardo", "profession": "32", "lastName": "Marques", "age": "33", "regionId": "27", "regionalCode": "0", "bibId": "", "profilePicS3key": "pukie.png", "scores": [{"score": "12960000", "scoreDisplay": "296 reps"}], "affiliateName": "Go Piat\u00e3 CrossFit", "affiliateId": "20153", "competitorName": "Ricardo Marques", "teamCaptain": "0", "gender": "M", "divisionId": "1", "height": "184 cm", "regionName": "South America"}, {"status": "ACT", "competitorId": "1031468", "countryShortCode": "", "weight": "76 kg", "firstName": "Igor", "profession": "0", "lastName": "Cerqueira", "age": "35", "regionId": "27", "regionalCode": "0", "bibId": "", "profilePicS3key": "e6e0d-P1031468_5-184.jpg", "scores": [{"score": "12960000", "scoreDisplay": "296 reps"}], "affiliateName": "CrossFit SSA", "affiliateId": "13482", "competitorName": "Igor Cerqueira", "teamCaptain": "0", "gender": "M", "divisionId": "18", "height": "170 cm", "regionName": "South America"}, {"status": "ACT", "competitorId": "1251071", "countryShortCode": "", "weight": "", "firstName": "Jo\u00e3o Felipe", "profession": "1", "lastName": "Santos", "age": "32", "regionId": "27", "regionalCode": "0", "bibId": "", "profilePicS3key": "3d11c-P1251071_2-184.jpg", "scores": [{"score": "12960000", "scoreDisplay": "296 reps"}], "affiliateName": "Pulsar CrossFit", "affiliateId": "11246", "competitorName": "Jo\u00e3o Felipe Santos", "teamCaptain": "0", "gender": "M", "divisionId": "1", "height": "", "regionName": "South America"}, {"status": "ACT", "competitorId": "864553", "countryShortCode": "", "weight": "", "firstName": "Lucas Camprigher", "profession": "0", "lastName": "d'Utra", "age": "25", "regionId": "27", "regionalCode": "0", "bibId": "", "profilePicS3key": "pukie.png", "scores": [{"score": "12960000", "scoreDisplay": "296 reps"}], "affiliateName": "Pulsar CrossFit", "affiliateId": "11246", "competitorName": "Lucas Camprigher d'Utra", "teamCaptain": "0", "gender": "M", "divisionId": "1", "height": "", "regionName": "South America"}, {"status": "ACT", "competitorId": "806747", "countryShortCode": "", "weight": "", "firstName": "Jorge", "profession": "0", "lastName": "Pereira", "age": "30", "regionId": "27", "regionalCode": "0", "bibId": "", "profilePicS3key": "f48e1-P806747_3-184.jpg", "scores": [{"score": "12960000", "scoreDisplay": "296 reps"}], "affiliateName": "Pulsar CrossFit", "affiliateId": "11246", "competitorName": "Jorge Pereira", "teamCaptain": "0", "gender": "M", "divisionId": "1", "height": "", "regionName": "South America"}, {"status": "ACT", "competitorId": "489737", "countryShortCode": "", "weight": "88 kg", "firstName": "Guilherme", "profession": "0", "lastName": "Cerqueira", "age": "30", "regionId": "27", "regionalCode": "0", "bibId": "", "profilePicS3key": "0d0c8-P489737_4-184.jpg", "scores": [{"score": "12920000", "scoreDisplay": "292 reps"}], "affiliateName": "Aldeia CrossFit", "affiliateId": "10632", "competitorName": "Guilherme Cerqueira", "teamCaptain": "0", "gender": "M", "divisionId": "1", "height": "177 cm", "regionName": "South America"}, {"status": "ACT", "competitorId": "1393732", "countryShortCode": "", "weight": "90 kg", "firstName": "Rangel", "profession": "128", "lastName": "Peruna", "age": "29", "regionId": "27", "regionalCode": "0", "bibId": "", "profilePicS3key": "e66a6-P1393732_1-184.jpg", "scores": [{"score": "12900000", "scoreDisplay": "290 reps"}], "affiliateName": "Go Piat\u00e3 CrossFit", "affiliateId": "20153", "competitorName": "Rangel Peruna", "teamCaptain": "0", "gender": "M", "divisionId": "1", "height": "185 cm", "regionName": "South America"}, {"status": "ACT", "competitorId": "408905", "countryShortCode": "", "weight": "88 kg", "firstName": "Leonardo", "profession": "256", "lastName": "Stanziola", "age": "26", "regionId": "27", "regionalCode": "0", "bibId": "", "profilePicS3key": "a1dec-P408905_3-184.jpg", "scores": [{"score": "12880000", "scoreDisplay": "288 reps"}], "affiliateName": "Garagem 164 CrossFit", "affiliateId": "17676", "competitorName": "Leonardo Stanziola", "teamCaptain": "0", "gender": "M", "divisionId": "1", "height": "178 cm", "regionName": "South America"}, {"status": "ACT", "competitorId": "458756", "countryShortCode": "", "weight": "76 kg", "firstName": "Tasso", "profession": "0", "lastName": "Tourinho", "age": "32", "regionId": "27", "regionalCode": "0", "bibId": "", "profilePicS3key": "b0a55-P458756_4-184.jpg", "scores": [{"score": "12880000", "scoreDisplay": "288 reps"}], "affiliateName": "CrossFit OnzeOnze", "affiliateId": "16711", "competitorName": "Tasso Tourinho", "teamCaptain": "0", "gender": "M", "divisionId": "1", "height": "176 cm", "regionName": "South America"}, {"status": "ACT", "competitorId": "1412194", "countryShortCode": "", "weight": "", "firstName": "\u00c1lvaro", "profession": "0", "lastName": "Miranda", "age": "31", "regionId": "27", "regionalCode": "0", "bibId": "", "profilePicS3key": "pukie.png", "scores": [{"score": "12880000", "scoreDisplay": "288 reps"}], "affiliateName": "CrossFit OnzeOnze", "affiliateId": "16711", "competitorName": "\u00c1lvaro Miranda", "teamCaptain": "0", "gender": "M", "divisionId": "1", "height": "", "regionName": "South America"}, {"status": "ACT", "competitorId": "791972", "countryShortCode": "", "weight": "83 kg", "firstName": "Ivan", "profession": "0", "lastName": "Araujo", "age": "33", "regionId": "27", "regionalCode": "0", "bibId": "", "profilePicS3key": "9347a-P791972_1-184.jpg", "scores": [{"score": "12880000", "scoreDisplay": "288 reps"}], "affiliateName": "Pulsar CrossFit", "affiliateId": "11246", "competitorName": "Ivan Araujo", "teamCaptain": "0", "gender": "M", "divisionId": "1", "height": "178 cm", "regionName": "South America"}, {"status": "ACT", "competitorId": "973570", "countryShortCode": "", "weight": "82 kg", "firstName": "Caio", "profession": "0", "lastName": "Castro", "age": "31", "regionId": "27", "regionalCode": "0", "bibId": "", "profilePicS3key": "pukie.png", "scores": [{"score": "12880000", "scoreDisplay": "288 reps"}], "affiliateName": "CrossFit Barra Action", "affiliateId": "8031", "competitorName": "Caio Castro", "teamCaptain": "0", "gender": "M", "divisionId": "1", "height": "", "regionName": "South America"}, {"status": "ACT", "competitorId": "869130", "countryShortCode": "", "weight": "73 kg", "firstName": "Tecio", "profession": "0", "lastName": "Carvalho", "age": "44", "regionId": "27", "regionalCode": "0", "bibId": "", "profilePicS3key": "b28a5-P869130_2-184.jpg", "scores": [{"score": "12880000", "scoreDisplay": "288 reps"}], "affiliateName": "CrossFit Jequie", "affiliateId": "7442", "competitorName": "Tecio Carvalho", "teamCaptain": "0", "gender": "M", "divisionId": "12", "height": "182 cm", "regionName": "South America"}, {"status": "ACT", "competitorId": "1265084", "countryShortCode": "", "weight": "82 kg", "firstName": "Greg\u00f3rio", "profession": "1", "lastName": "Junior", "age": "34", "regionId": "27", "regionalCode": "0", "bibId": "", "profilePicS3key": "a46ae-P1265084_1-184.jpg", "scores": [{"score": "12880000", "scoreDisplay": "288 reps"}], "affiliateName": "CrossFit Jequie", "affiliateId": "7442", "competitorName": "Greg\u00f3rio Junior", "teamCaptain": "0", "gender": "M", "divisionId": "1", "height": "180 cm", "regionName": "South America"}, {"status": "ACT", "competitorId": "455342", "countryShortCode": "", "weight": "83 kg", "firstName": "Tales", "profession": "0", "lastName": "Bahia", "age": "30", "regionId": "27", "regionalCode": "0", "bibId": "", "profilePicS3key": "04ec1-P455342_4-184.jpg", "scores": [{"score": "12870000", "scoreDisplay": "287 reps"}], "affiliateName": "CrossFit MALTA", "affiliateId": "19903", "competitorName": "Tales Bahia", "teamCaptain": "0", "gender": "M", "divisionId": "1", "height": "179 cm", "regionName": "South America"}, {"status": "ACT", "competitorId": "893720", "countryShortCode": "", "weight": "79 kg", "firstName": "M\u00e1rio Felipe", "profession": "128", "lastName": "Pedreira Neto", "age": "30", "regionId": "27", "regionalCode": "0", "bibId": "", "profilePicS3key": "ecd3a-P893720_6-184.jpg", "scores": [{"score": "12870000", "scoreDisplay": "287 reps"}], "affiliateName": "CrossFit Barra Action", "affiliateId": "8031", "competitorName": "M\u00e1rio Felipe Pedreira Neto", "teamCaptain": "0", "gender": "M", "divisionId": "1", "height": "181 cm", "regionName": "South America"}, {"status": "ACT", "competitorId": "978191", "countryShortCode": "", "weight": "81 kg", "firstName": "Bruno", "profession": "256", "lastName": "Alves", "age": "26", "regionId": "27", "regionalCode": "0", "bibId": "", "profilePicS3key": "13b3c-P978191_1-184.jpg", "scores": [{"score": "12840000", "scoreDisplay": "284 reps"}], "affiliateName": "Garagem 164 CrossFit", "affiliateId": "17676", "competitorName": "Bruno Alves", "teamCaptain": "0", "gender": "M", "divisionId": "1", "height": "177 cm", "regionName": "South America"}, {"status": "ACT", "competitorId": "756784", "countryShortCode": "", "weight": "92 kg", "firstName": "Rafael Pinto", "profession": "0", "lastName": "Coelho", "age": "35", "regionId": "27", "regionalCode": "0", "bibId": "", "profilePicS3key": "7bf40-P756784_2-184.jpg", "scores": [{"score": "12830000", "scoreDisplay": "283 reps"}], "affiliateName": "Go Piat\u00e3 CrossFit", "affiliateId": "20153", "competitorName": "Rafael Pinto Coelho", "teamCaptain": "0", "gender": "M", "divisionId": "18", "height": "188 cm", "regionName": "South America"}, {"status": "ACT", "competitorId": "1398552", "countryShortCode": "", "weight": "87 kg", "firstName": "Ulisses", "profession": "0", "lastName": "Coelho Lima Junior", "age": "32", "regionId": "27", "regionalCode": "0", "bibId": "", "profilePicS3key": "pukie.png", "scores": [{"score": "12820000", "scoreDisplay": "282 reps"}], "affiliateName": "Go Piat\u00e3 CrossFit", "affiliateId": "20153", "competitorName": "Ulisses Coelho Lima Junior", "teamCaptain": "0", "gender": "M", "divisionId": "1", "height": "", "regionName": "South America"}, {"status": "ACT", "competitorId": "943535", "countryShortCode": "", "weight": "90 kg", "firstName": "Tiago", "profession": "0", "lastName": "Porto", "age": "31", "regionId": "27", "regionalCode": "0", "bibId": "", "profilePicS3key": "05c29-P943535_2-184.jpg", "scores": [{"score": "12820000", "scoreDisplay": "282 reps"}], "affiliateName": "CrossFit Maral", "affiliateId": "16225", "competitorName": "Tiago Porto", "teamCaptain": "0", "gender": "M", "divisionId": "1", "height": "184 cm", "regionName": "South America"}, {"status": "ACT", "competitorId": "1027573", "countryShortCode": "", "weight": "73 kg", "firstName": "Jo\u00e3o Roberto", "profession": "0", "lastName": "Nogueira da Silva", "age": "25", "regionId": "27", "regionalCode": "0", "bibId": "", "profilePicS3key": "pukie.png", "scores": [{"score": "12810000", "scoreDisplay": "281 reps"}], "affiliateName": "CrossFit OnzeOnze", "affiliateId": "16711", "competitorName": "Jo\u00e3o Roberto Nogueira da Silva", "teamCaptain": "0", "gender": "M", "divisionId": "1", "height": "173 cm", "regionName": "South America"}, {"status": "ACT", "competitorId": "902322", "countryShortCode": "", "weight": "82 kg", "firstName": "Guilherme", "profession": "0", "lastName": "Guarda", "age": "27", "regionId": "27", "regionalCode": "0", "bibId": "", "profilePicS3key": "187f8-P902322_1-184.jpg", "scores": [{"score": "12800000", "scoreDisplay": "280 reps"}], "affiliateName": "CrossFit Alcateia", "affiliateId": "12275", "competitorName": "Guilherme Guarda", "teamCaptain": "0", "gender": "M", "divisionId": "1", "height": "180 cm", "regionName": "South America"}, {"status": "ACT", "competitorId": "890585", "countryShortCode": "", "weight": "73 kg", "firstName": "Marcello", "profession": "0", "lastName": "Abreu", "age": "28", "regionId": "27", "regionalCode": "0", "bibId": "", "profilePicS3key": "e80d0-P890585_1-184.jpg", "scores": [{"score": "12790000", "scoreDisplay": "279 reps"}], "affiliateName": "CrossFit SSA", "affiliateId": "13482", "competitorName": "Marcello Abreu", "teamCaptain": "0", "gender": "M", "divisionId": "1", "height": "171 cm", "regionName": "South America"}, {"status": "ACT", "competitorId": "948114", "countryShortCode": "", "weight": "73 kg", "firstName": "Kayo", "profession": "0", "lastName": "Barboza", "age": "31", "regionId": "27", "regionalCode": "0", "bibId": "", "profilePicS3key": "56a71-P948114_1-184.jpg", "scores": [{"score": "12770000", "scoreDisplay": "277 reps"}], "affiliateName": "CrossFit MALTA", "affiliateId": "19903", "competitorName": "Kayo Barboza", "teamCaptain": "0", "gender": "M", "divisionId": "1", "height": "176 cm", "regionName": "South America"}, {"status": "ACT", "competitorId": "762707", "countryShortCode": "", "weight": "76 kg", "firstName": "Rafael", "profession": "0", "lastName": "Cheffer", "age": "30", "regionId": "27", "regionalCode": "0", "bibId": "", "profilePicS3key": "f6554-P762707_2-184.jpg", "scores": [{"score": "12750000", "scoreDisplay": "275 reps"}], "affiliateName": "Go Piat\u00e3 CrossFit", "affiliateId": "20153", "competitorName": "Rafael Cheffer", "teamCaptain": "0", "gender": "M", "divisionId": "1", "height": "178 cm", "regionName": "South America"}, {"status": "ACT", "competitorId": "1342988", "countryShortCode": "", "weight": "", "firstName": "Gillis", "profession": "0", "lastName": "Bastos", "age": "36", "regionId": "27", "regionalCode": "0", "bibId": "", "profilePicS3key": "pukie.png", "scores": [{"score": "12750000", "scoreDisplay": "275 reps"}], "affiliateName": "CrossFit 7373", "affiliateId": "18390", "competitorName": "Gillis Bastos", "teamCaptain": "0", "gender": "M", "divisionId": "18", "height": "", "regionName": "South America"}, {"status": "ACT", "competitorId": "959857", "countryShortCode": "", "weight": "", "firstName": "Henrique", "profession": "4", "lastName": "Barreto", "age": "35", "regionId": "27", "regionalCode": "0", "bibId": "", "profilePicS3key": "pukie.png", "scores": [{"score": "12740000", "scoreDisplay": "274 reps"}], "affiliateName": "CrossFit OnzeOnze", "affiliateId": "16711", "competitorName": "Henrique Barreto", "teamCaptain": "0", "gender": "M", "divisionId": "18", "height": "", "regionName": "South America"}, {"status": "ACT", "competitorId": "816068", "countryShortCode": "", "weight": "87 kg", "firstName": "Glauco", "profession": "0", "lastName": "Ba\u00eda", "age": "35", "regionId": "27", "regionalCode": "0", "bibId": "", "profilePicS3key": "92f76-P816068_2-184.jpg", "scores": [{"score": "12740000", "scoreDisplay": "274 reps"}], "affiliateName": "Aldeia CrossFit", "affiliateId": "10632", "competitorName": "Glauco Ba\u00eda", "teamCaptain": "0", "gender": "M", "divisionId": "18", "height": "181 cm", "regionName": "South America"}, {"status": "ACT", "competitorId": "920642", "countryShortCode": "", "weight": "78 kg", "firstName": "Lucas", "profession": "0", "lastName": "Conceicao", "age": "23", "regionId": "27", "regionalCode": "0", "bibId": "", "profilePicS3key": "e1798-P920642_1-184.jpg", "scores": [{"score": "12730000", "scoreDisplay": "273 reps"}], "affiliateName": "Pulsar CrossFit", "affiliateId": "11246", "competitorName": "Lucas Conceicao", "teamCaptain": "0", "gender": "M", "divisionId": "1", "height": "173 cm", "regionName": "South America"}, {"status": "ACT", "competitorId": "1350088", "countryShortCode": "", "weight": "", "firstName": "Diego", "profession": "0", "lastName": "Cunha", "age": "32", "regionId": "27", "regionalCode": "0", "bibId": "", "profilePicS3key": "pukie.png", "scores": [{"score": "12720000", "scoreDisplay": "272 reps"}], "affiliateName": "CrossFit OnzeOnze", "affiliateId": "16711", "competitorName": "Diego Cunha", "teamCaptain": "0", "gender": "M", "divisionId": "1", "height": "", "regionName": "South America"}, {"status": "ACT", "competitorId": "1241102", "countryShortCode": "", "weight": "89 kg", "firstName": "Jorge", "profession": "128", "lastName": "Rios de Oliveira", "age": "37", "regionId": "27", "regionalCode": "0", "bibId": "", "profilePicS3key": "9c4a1-P1241102_1-184.jpg", "scores": [{"score": "12720000", "scoreDisplay": "272 reps"}], "affiliateName": "CrossFit SSA", "affiliateId": "13482", "competitorName": "Jorge Rios de Oliveira", "teamCaptain": "0", "gender": "M", "divisionId": "18", "height": "", "regionName": "South America"}, {"status": "ACT", "competitorId": "889268", "countryShortCode": "", "weight": "72 kg", "firstName": "Cristiano", "profession": "0", "lastName": "Santos", "age": "24", "regionId": "27", "regionalCode": "0", "bibId": "", "profilePicS3key": "622dc-P889268_1-184.jpg", "scores": [{"score": "12700000", "scoreDisplay": "270 reps"}], "affiliateName": "CrossFit Maral", "affiliateId": "16225", "competitorName": "Cristiano Santos", "teamCaptain": "0", "gender": "M", "divisionId": "1", "height": "177 cm", "regionName": "South America"}, {"status": "ACT", "competitorId": "1280812", "countryShortCode": "", "weight": "83 kg", "firstName": "Matheus", "profession": "128", "lastName": "Lopes", "age": "25", "regionId": "27", "regionalCode": "0", "bibId": "", "profilePicS3key": "fcfc1-P1280812_1-184.jpg", "scores": [{"score": "12700000", "scoreDisplay": "270 reps"}], "affiliateName": "CrossFit Maral", "affiliateId": "16225", "competitorName": "Matheus Lopes", "teamCaptain": "0", "gender": "M", "divisionId": "1", "height": "173 cm", "regionName": "South America"}, {"status": "ACT", "competitorId": "1411526", "countryShortCode": "", "weight": "84 kg", "firstName": "Rodrigo", "profession": "128", "lastName": "Mac\u00eado", "age": "24", "regionId": "27", "regionalCode": "0", "bibId": "", "profilePicS3key": "67efb-P1411526_1-184.jpg", "scores": [{"score": "12700000", "scoreDisplay": "270 reps"}], "affiliateName": "Pulsar CrossFit", "affiliateId": "11246", "competitorName": "Rodrigo Mac\u00eado", "teamCaptain": "0", "gender": "M", "divisionId": "1", "height": "", "regionName": "South America"}, {"status": "ACT", "competitorId": "1286926", "countryShortCode": "", "weight": "87 kg", "firstName": "Nivaldo", "profession": "0", "lastName": "Muritiba", "age": "24", "regionId": "27", "regionalCode": "0", "bibId": "", "profilePicS3key": "cc9d8-P1286926_1-184.jpg", "scores": [{"score": "12680000", "scoreDisplay": "268 reps"}], "affiliateName": "CrossFit Maral", "affiliateId": "16225", "competitorName": "Nivaldo Muritiba", "teamCaptain": "0", "gender": "M", "divisionId": "1", "height": "176 cm", "regionName": "South America"}, {"status": "ACT", "competitorId": "1370299", "countryShortCode": "", "weight": "", "firstName": "Gabriel", "profession": "0", "lastName": "Carvalho", "age": "24", "regionId": "27", "regionalCode": "0", "bibId": "", "profilePicS3key": "pukie.png", "scores": [{"score": "12670000", "scoreDisplay": "267 reps"}], "affiliateName": "Go Piat\u00e3 CrossFit", "affiliateId": "20153", "competitorName": "Gabriel Carvalho", "teamCaptain": "0", "gender": "M", "divisionId": "1", "height": "", "regionName": "South America"}, {"status": "ACT", "competitorId": "218952", "countryShortCode": "", "weight": "80 kg", "firstName": "Danillo", "profession": "0", "lastName": "Dattoli", "age": "37", "regionId": "27", "regionalCode": "0", "bibId": "", "profilePicS3key": "aa642-P218952_5-184.jpg", "scores": [{"score": "12670000", "scoreDisplay": "267 reps"}], "affiliateName": "CrossFit Jequie", "affiliateId": "7442", "competitorName": "Danillo Dattoli", "teamCaptain": "0", "gender": "M", "divisionId": "18", "height": "179 cm", "regionName": "South America"}, {"status": "ACT", "competitorId": "1339192", "countryShortCode": "", "weight": "", "firstName": "Rafael", "profession": "0", "lastName": "Magalh\u00e3es", "age": "24", "regionId": "27", "regionalCode": "0", "bibId": "", "profilePicS3key": "c21f8-P1339192_1-184.jpg", "scores": [{"score": "12650000", "scoreDisplay": "265 reps"}], "affiliateName": "CrossFit 7373", "affiliateId": "18390", "competitorName": "Rafael Magalh\u00e3es", "teamCaptain": "0", "gender": "M", "divisionId": "1", "height": "", "regionName": "South America"}, {"status": "ACT", "competitorId": "1205820", "countryShortCode": "", "weight": "90 kg", "firstName": "Mateus", "profession": "1", "lastName": "Gon\u00e7alves", "age": "31", "regionId": "27", "regionalCode": "0", "bibId": "", "profilePicS3key": "b197a-P1205820_1-184.jpg", "scores": [{"score": "12650000", "scoreDisplay": "265 reps"}], "affiliateName": "Pulsar CrossFit", "affiliateId": "11246", "competitorName": "Mateus Gon\u00e7alves", "teamCaptain": "0", "gender": "M", "divisionId": "1", "height": "188 cm", "regionName": "South America"}, {"status": "ACT", "competitorId": "753262", "countryShortCode": "", "weight": "82 kg", "firstName": "Gabriel", "profession": "0", "lastName": "Novaes", "age": "32", "regionId": "27", "regionalCode": "0", "bibId": "", "profilePicS3key": "0cc47-P753262_1-184.jpg", "scores": [{"score": "12650000", "scoreDisplay": "265 reps"}], "affiliateName": "Aldeia CrossFit", "affiliateId": "10632", "competitorName": "Gabriel Novaes", "teamCaptain": "0", "gender": "M", "divisionId": "1", "height": "174 cm", "regionName": "South America"}, {"status": "ACT", "competitorId": "1057762", "countryShortCode": "", "weight": "89 kg", "firstName": "Guttenberg", "profession": "0", "lastName": "Braun", "age": "44", "regionId": "27", "regionalCode": "0", "bibId": "", "profilePicS3key": "20e6a-P1057762_2-184.jpg", "scores": [{"score": "12640000", "scoreDisplay": "264 reps"}], "affiliateName": "Garagem 164 CrossFit", "affiliateId": "17676", "competitorName": "Guttenberg Braun", "teamCaptain": "0", "gender": "M", "divisionId": "12", "height": "181 cm", "regionName": "South America"}, {"status": "ACT", "competitorId": "1228090", "countryShortCode": "", "weight": "78 kg", "firstName": "Tiago", "profession": "256", "lastName": "Mimoso", "age": "38", "regionId": "27", "regionalCode": "0", "bibId": "", "profilePicS3key": "92832-P1228090_2-184.jpg", "scores": [{"score": "12640000", "scoreDisplay": "264 reps"}], "affiliateName": "CrossFit Oxente", "affiliateId": "16767", "competitorName": "Tiago Mimoso", "teamCaptain": "0", "gender": "M", "divisionId": "18", "height": "176 cm", "regionName": "South America"}, {"status": "ACT", "competitorId": "144794", "countryShortCode": "", "weight": "191 lb", "firstName": "Ronaldo", "profession": "0", "lastName": "Tannus", "age": "40", "regionId": "27", "regionalCode": "0", "bibId": "", "profilePicS3key": "1149a-P144794_2-184.jpg", "scores": [{"score": "12640000", "scoreDisplay": "264 reps"}], "affiliateName": "CrossFit Barra Action", "affiliateId": "8031", "competitorName": "Ronaldo Tannus", "teamCaptain": "0", "gender": "M", "divisionId": "12", "height": "186 cm", "regionName": "South America"}, {"status": "ACT", "competitorId": "902103", "countryShortCode": "", "weight": "90 kg", "firstName": "Alcides", "profession": "128", "lastName": "Rocha", "age": "17", "regionId": "27", "regionalCode": "0", "bibId": "", "profilePicS3key": "fc376-P902103_3-184.jpg", "scores": [{"score": "12630000", "scoreDisplay": "263 reps"}], "affiliateName": "CrossFit OnzeOnze", "affiliateId": "16711", "competitorName": "Alcides Rocha", "teamCaptain": "0", "gender": "M", "divisionId": "16", "height": "186 cm", "regionName": "South America"}, {"status": "ACT", "competitorId": "1215546", "countryShortCode": "", "weight": "68 kg", "firstName": "Rafael", "profession": "0", "lastName": "Matos", "age": "28", "regionId": "27", "regionalCode": "0", "bibId": "", "profilePicS3key": "03654-P1215546_1-184.jpg", "scores": [{"score": "12630000", "scoreDisplay": "263 reps"}], "affiliateName": "Summer CrossFit", "affiliateId": "15017", "competitorName": "Rafael Matos", "teamCaptain": "0", "gender": "M", "divisionId": "1", "height": "169 cm", "regionName": "South America"}, {"status": "ACT", "competitorId": "1244765", "countryShortCode": "", "weight": "", "firstName": "Frederico", "profession": "0", "lastName": "Pimwntel", "age": "29", "regionId": "27", "regionalCode": "0", "bibId": "", "profilePicS3key": "pukie.png", "scores": [{"score": "12630000", "scoreDisplay": "263 reps"}], "affiliateName": "CrossFit Alcateia", "affiliateId": "12275", "competitorName": "Frederico Pimwntel", "teamCaptain": "0", "gender": "M", "divisionId": "1", "height": "", "regionName": "South America"}, {"status": "ACT", "competitorId": "643174", "countryShortCode": "", "weight": "", "firstName": "Fabio", "profession": "0", "lastName": "Orleans", "age": "34", "regionId": "27", "regionalCode": "0", "bibId": "", "profilePicS3key": "pukie.png", "scores": [{"score": "12630000", "scoreDisplay": "263 reps"}], "affiliateName": "Aldeia CrossFit", "affiliateId": "10632", "competitorName": "Fabio Orleans", "teamCaptain": "0", "gender": "M", "divisionId": "1", "height": "", "regionName": "South America"}, {"status": "ACT", "competitorId": "1339340", "countryShortCode": "", "weight": "", "firstName": "Eust\u00e1quio", "profession": "0", "lastName": "Lacerda", "age": "29", "regionId": "27", "regionalCode": "0", "bibId": "", "profilePicS3key": "pukie.png", "scores": [{"score": "12620000", "scoreDisplay": "262 reps"}], "affiliateName": "CrossFit 7373", "affiliateId": "18390", "competitorName": "Eust\u00e1quio Lacerda", "teamCaptain": "0", "gender": "M", "divisionId": "1", "height": "", "regionName": "South America"}, {"status": "ACT", "competitorId": "661876", "countryShortCode": "", "weight": "", "firstName": "Alexandre", "profession": "0", "lastName": "Winter", "age": "35", "regionId": "27", "regionalCode": "0", "bibId": "", "profilePicS3key": "pukie.png", "scores": [{"score": "12620000", "scoreDisplay": "262 reps"}], "affiliateName": "CrossFit Alcateia", "affiliateId": "12275", "competitorName": "Alexandre Winter", "teamCaptain": "0", "gender": "M", "divisionId": "18", "height": "", "regionName": "South America"}, {"status": "ACT", "competitorId": "1369295", "countryShortCode": "", "weight": "70 kg", "firstName": "Filipe", "profession": "64", "lastName": "Esteves", "age": "28", "regionId": "27", "regionalCode": "0", "bibId": "", "profilePicS3key": "b0fa5-P1369295_1-184.jpg", "scores": [{"score": "12620000", "scoreDisplay": "262 reps"}], "affiliateName": "Aldeia CrossFit", "affiliateId": "10632", "competitorName": "Filipe Esteves", "teamCaptain": "0", "gender": "M", "divisionId": "1", "height": "169 cm", "regionName": "South America"}, {"status": "ACT", "competitorId": "1221784", "countryShortCode": "", "weight": "90 kg", "firstName": "Alex", "profession": "0", "lastName": "Aguiar", "age": "28", "regionId": "27", "regionalCode": "0", "bibId": "", "profilePicS3key": "782ee-P1221784_1-184.jpg", "scores": [{"score": "12610000", "scoreDisplay": "261 reps"}], "affiliateName": "CrossFit OnzeOnze", "affiliateId": "16711", "competitorName": "Alex Aguiar", "teamCaptain": "0", "gender": "M", "divisionId": "1", "height": "176 cm", "regionName": "South America"}, {"status": "ACT", "competitorId": "1271151", "countryShortCode": "", "weight": "", "firstName": "Victor", "profession": "0", "lastName": "Miranda", "age": "23", "regionId": "27", "regionalCode": "0", "bibId": "", "profilePicS3key": "702e0-P1271151_1-184.jpg", "scores": [{"score": "12590000", "scoreDisplay": "259 reps"}], "affiliateName": "Aldeia CrossFit", "affiliateId": "10632", "competitorName": "Victor Miranda", "teamCaptain": "0", "gender": "M", "divisionId": "1", "height": "", "regionName": "South America"}, {"status": "ACT", "competitorId": "1411545", "countryShortCode": "", "weight": "86 kg", "firstName": "Lucas", "profession": "128", "lastName": "Costa", "age": "24", "regionId": "27", "regionalCode": "0", "bibId": "", "profilePicS3key": "327a0-P1411545_1-184.jpg", "scores": [{"score": "12580000", "scoreDisplay": "258 reps"}], "affiliateName": "Pulsar CrossFit", "affiliateId": "11246", "competitorName": "Lucas Costa", "teamCaptain": "0", "gender": "M", "divisionId": "1", "height": "", "regionName": "South America"}, {"status": "ACT", "competitorId": "1047450", "countryShortCode": "", "weight": "", "firstName": "Lucas", "profession": "0", "lastName": "Andrade", "age": "27", "regionId": "27", "regionalCode": "0", "bibId": "", "profilePicS3key": "pukie.png", "scores": [{"score": "12580000", "scoreDisplay": "258 reps"}], "affiliateName": "CrossFit Jequie", "affiliateId": "7442", "competitorName": "Lucas Andrade", "teamCaptain": "0", "gender": "M", "divisionId": "1", "height": "", "regionName": "South America"}, {"status": "ACT", "competitorId": "1134145", "countryShortCode": "", "weight": "177 lb", "firstName": "Charles", "profession": "256", "lastName": "Monteiro", "age": "27", "regionId": "27", "regionalCode": "0", "bibId": "", "profilePicS3key": "d41ec-P1134145_1-184.jpg", "scores": [{"score": "12560000", "scoreDisplay": "256 reps"}], "affiliateName": "CrossFit 7373", "affiliateId": "18390", "competitorName": "Charles Monteiro", "teamCaptain": "0", "gender": "M", "divisionId": "1", "height": "180 in", "regionName": "South America"}, {"status": "ACT", "competitorId": "1240459", "countryShortCode": "", "weight": "", "firstName": "Joao Gabriel", "profession": "0", "lastName": "Susin Castro", "age": "32", "regionId": "27", "regionalCode": "0", "bibId": "", "profilePicS3key": "15446-P1240459_1-184.jpg", "scores": [{"score": "12560000", "scoreDisplay": "256 reps"}], "affiliateName": "Garagem 164 CrossFit", "affiliateId": "17676", "competitorName": "Joao Gabriel Susin Castro", "teamCaptain": "0", "gender": "M", "divisionId": "1", "height": "", "regionName": "South America"}, {"status": "ACT", "competitorId": "705234", "countryShortCode": "", "weight": "77 kg", "firstName": "Rafael", "profession": "0", "lastName": "Chaves", "age": "33", "regionId": "27", "regionalCode": "0", "bibId": "", "profilePicS3key": "e8c32-P705234_1-184.jpg", "scores": [{"score": "12560000", "scoreDisplay": "256 reps"}], "affiliateName": "Pulsar CrossFit", "affiliateId": "11246", "competitorName": "Rafael Chaves", "teamCaptain": "0", "gender": "M", "divisionId": "1", "height": "173 cm", "regionName": "South America"}, {"status": "ACT", "competitorId": "1236567", "countryShortCode": "", "weight": "82 kg", "firstName": "Richard", "profession": "128", "lastName": "Saback", "age": "34", "regionId": "27", "regionalCode": "0", "bibId": "", "profilePicS3key": "bcbec-P1236567_1-184.jpg", "scores": [{"score": "12560000", "scoreDisplay": "256 reps"}], "affiliateName": "Aldeia CrossFit", "affiliateId": "10632", "competitorName": "Richard Saback", "teamCaptain": "0", "gender": "M", "divisionId": "1", "height": "181 cm", "regionName": "South America"}, {"status": "ACT", "competitorId": "791233", "countryShortCode": "", "weight": "", "firstName": "Genilson", "profession": "0", "lastName": "Machado", "age": "29", "regionId": "27", "regionalCode": "0", "bibId": "", "profilePicS3key": "pukie.png", "scores": [{"score": "12560000", "scoreDisplay": "256 reps"}], "affiliateName": "Aldeia CrossFit", "affiliateId": "10632", "competitorName": "Genilson Machado", "teamCaptain": "0", "gender": "M", "divisionId": "1", "height": "", "regionName": "South America"}, {"status": "ACT", "competitorId": "879781", "countryShortCode": "", "weight": "86 kg", "firstName": "Vinicius", "profession": "0", "lastName": "Soeiro", "age": "29", "regionId": "27", "regionalCode": "0", "bibId": "", "profilePicS3key": "6645f-P879781_2-184.jpg", "scores": [{"score": "12530000", "scoreDisplay": "253 reps"}], "affiliateName": "CrossFit OnzeOnze", "affiliateId": "16711", "competitorName": "Vinicius Soeiro", "teamCaptain": "0", "gender": "M", "divisionId": "1", "height": "178 cm", "regionName": "South America"}, {"status": "ACT", "competitorId": "1243293", "countryShortCode": "", "weight": "79 kg", "firstName": "Diogo", "profession": "0", "lastName": "Gomes", "age": "32", "regionId": "27", "regionalCode": "0", "bibId": "", "profilePicS3key": "f32fb-P1243293_1-184.jpg", "scores": [{"score": "12520000", "scoreDisplay": "252 reps"}], "affiliateName": "Go Piat\u00e3 CrossFit", "affiliateId": "20153", "competitorName": "Diogo Gomes", "teamCaptain": "0", "gender": "M", "divisionId": "1", "height": "175 cm", "regionName": "South America"}, {"status": "ACT", "competitorId": "981778", "countryShortCode": "", "weight": "82 kg", "firstName": "Gustavo", "profession": "0", "lastName": "Ferreira", "age": "40", "regionId": "27", "regionalCode": "0", "bibId": "", "profilePicS3key": "pukie.png", "scores": [{"score": "12510000", "scoreDisplay": "251 reps"}], "affiliateName": "Aldeia CrossFit", "affiliateId": "10632", "competitorName": "Gustavo Ferreira", "teamCaptain": "0", "gender": "M", "divisionId": "12", "height": "", "regionName": "South America"}, {"status": "ACT", "competitorId": "1343729", "countryShortCode": "", "weight": "", "firstName": "Pedro", "profession": "128", "lastName": "Ortins", "age": "26", "regionId": "27", "regionalCode": "0", "bibId": "", "profilePicS3key": "pukie.png", "scores": [{"score": "12490000", "scoreDisplay": "249 reps"}], "affiliateName": "Aldeia CrossFit", "affiliateId": "10632", "competitorName": "Pedro Ortins", "teamCaptain": "0", "gender": "M", "divisionId": "1", "height": "", "regionName": "South America"}, {"status": "ACT", "competitorId": "1213489", "countryShortCode": "", "weight": "", "firstName": "Mauricio", "profession": "0", "lastName": "Reina", "age": "34", "regionId": "27", "regionalCode": "0", "bibId": "", "profilePicS3key": "f6769-P1213489_1-184.jpg", "scores": [{"score": "12480000", "scoreDisplay": "248 reps"}], "affiliateName": "CrossFit OnzeOnze", "affiliateId": "16711", "competitorName": "Mauricio Reina", "teamCaptain": "0", "gender": "M", "divisionId": "1", "height": "", "regionName": "South America"}, {"status": "ACT", "competitorId": "1325862", "countryShortCode": "", "weight": "79 kg", "firstName": "R\u00f4mulo", "profession": "256", "lastName": "Novaes", "age": "33", "regionId": "27", "regionalCode": "0", "bibId": "", "profilePicS3key": "ae6e7-P1325862_1-184.jpg", "scores": [{"score": "12480000", "scoreDisplay": "248 reps"}], "affiliateName": "CrossFit OnzeOnze", "affiliateId": "16711", "competitorName": "R\u00f4mulo Novaes", "teamCaptain": "0", "gender": "M", "divisionId": "1", "height": "", "regionName": "South America"}, {"status": "ACT", "competitorId": "979275", "countryShortCode": "", "weight": "70 kg", "firstName": "Caio", "profession": "0", "lastName": "Guarda", "age": "30", "regionId": "27", "regionalCode": "0", "bibId": "", "profilePicS3key": "a9ef8-P979275_1-184.jpg", "scores": [{"score": "12480000", "scoreDisplay": "248 reps"}], "affiliateName": "CrossFit Jequie", "affiliateId": "7442", "competitorName": "Caio Guarda", "teamCaptain": "0", "gender": "M", "divisionId": "1", "height": "", "regionName": "South America"}, {"status": "ACT", "competitorId": "682426", "countryShortCode": "", "weight": "82 kg", "firstName": "Guilherme", "profession": "0", "lastName": "Nicholls", "age": "28", "regionId": "27", "regionalCode": "0", "bibId": "", "profilePicS3key": "0eac0-P682426_2-184.jpg", "scores": [{"score": "12460000", "scoreDisplay": "246 reps"}], "affiliateName": "CrossFit Oxente", "affiliateId": "16767", "competitorName": "Guilherme Nicholls", "teamCaptain": "0", "gender": "M", "divisionId": "1", "height": "180 cm", "regionName": "South America"}, {"status": "ACT", "competitorId": "422489", "countryShortCode": "", "weight": "158 lb", "firstName": "Flavio Espirito", "profession": "128", "lastName": "Santo", "age": "38", "regionId": "27", "regionalCode": "0", "bibId": "", "profilePicS3key": "48348-P422489_2-184.jpg", "scores": [{"score": "12460000", "scoreDisplay": "246 reps"}], "affiliateName": "Aldeia CrossFit", "affiliateId": "10632", "competitorName": "Flavio Espirito Santo", "teamCaptain": "0", "gender": "M", "divisionId": "18", "height": "171 cm", "regionName": "South America"}, {"status": "ACT", "competitorId": "911692", "countryShortCode": "", "weight": "", "firstName": "H\u00e9lio", "profession": "0", "lastName": "Rosado", "age": "24", "regionId": "27", "regionalCode": "0", "bibId": "", "profilePicS3key": "pukie.png", "scores": [{"score": "12450000", "scoreDisplay": "245 reps"}], "affiliateName": "CrossFit Oxente", "affiliateId": "16767", "competitorName": "H\u00e9lio Rosado", "teamCaptain": "0", "gender": "M", "divisionId": "1", "height": "", "regionName": "South America"}, {"status": "ACT", "competitorId": "841437", "countryShortCode": "", "weight": "", "firstName": "Francisco", "profession": "0", "lastName": "Vilar", "age": "31", "regionId": "27", "regionalCode": "0", "bibId": "", "profilePicS3key": "f9a7d-P841437_1-184.jpg", "scores": [{"score": "12440000", "scoreDisplay": "244 reps"}], "affiliateName": "CrossFit Barra Action", "affiliateId": "8031", "competitorName": "Francisco Vilar", "teamCaptain": "0", "gender": "M", "divisionId": "1", "height": "", "regionName": "South America"}, {"status": "ACT", "competitorId": "1348832", "countryShortCode": "", "weight": "110 kg", "firstName": "Ramon Louren\u00e7o", "profession": "128", "lastName": "Ara\u00fajo da SIlva", "age": "36", "regionId": "27", "regionalCode": "0", "bibId": "", "profilePicS3key": "4478c-P1348832_1-184.jpg", "scores": [{"score": "12430000", "scoreDisplay": "243 reps"}], "affiliateName": "CrossFit SSA", "affiliateId": "13482", "competitorName": "Ramon Louren\u00e7o Ara\u00fajo da SIlva", "teamCaptain": "0", "gender": "M", "divisionId": "18", "height": "", "regionName": "South America"}, {"status": "ACT", "competitorId": "724620", "countryShortCode": "", "weight": "200 lb", "firstName": "Artur", "profession": "0", "lastName": "Castilho", "age": "25", "regionId": "27", "regionalCode": "0", "bibId": "", "profilePicS3key": "cb8ba-P724620_1-184.jpg", "scores": [{"score": "12420000", "scoreDisplay": "242 reps"}], "affiliateName": "CrossFit 7373", "affiliateId": "18390", "competitorName": "Artur Castilho", "teamCaptain": "0", "gender": "M", "divisionId": "1", "height": "182 cm", "regionName": "South America"}, {"status": "ACT", "competitorId": "1411199", "countryShortCode": "", "weight": "85 kg", "firstName": "Ricardo", "profession": "256", "lastName": "Andrade", "age": "39", "regionId": "27", "regionalCode": "0", "bibId": "", "profilePicS3key": "6c363-P1411199_1-184.jpg", "scores": [{"score": "12420000", "scoreDisplay": "242 reps"}], "affiliateName": "CrossFit Oxente", "affiliateId": "16767", "competitorName": "Ricardo Andrade", "teamCaptain": "0", "gender": "M", "divisionId": "18", "height": "", "regionName": "South America"}, {"status": "ACT", "competitorId": "1325229", "countryShortCode": "", "weight": "", "firstName": "Gilgleuton", "profession": "0", "lastName": "Nunes de Andrade", "age": "21", "regionId": "27", "regionalCode": "0", "bibId": "", "profilePicS3key": "42ac8-P1325229_1-184.jpg", "scores": [{"score": "12420000", "scoreDisplay": "242 reps"}], "affiliateName": "CrossFit OnzeOnze", "affiliateId": "16711", "competitorName": "Gilgleuton Nunes de Andrade", "teamCaptain": "0", "gender": "M", "divisionId": "1", "height": "", "regionName": "South America"}, {"status": "ACT", "competitorId": "962078", "countryShortCode": "", "weight": "", "firstName": "Vin\u00edcius", "profession": "32", "lastName": "Satyro", "age": "30", "regionId": "27", "regionalCode": "0", "bibId": "", "profilePicS3key": "24feb-P962078_1-184.jpg", "scores": [{"score": "12420000", "scoreDisplay": "242 reps"}], "affiliateName": "Pulsar CrossFit", "affiliateId": "11246", "competitorName": "Vin\u00edcius Satyro", "teamCaptain": "0", "gender": "M", "divisionId": "1", "height": "", "regionName": "South America"}, {"status": "ACT", "competitorId": "1275274", "countryShortCode": "", "weight": "83 kg", "firstName": "Ramon", "profession": "1", "lastName": "Soares", "age": "33", "regionId": "27", "regionalCode": "0", "bibId": "", "profilePicS3key": "pukie.png", "scores": [{"score": "12420000", "scoreDisplay": "242 reps"}], "affiliateName": "CrossFit Jequie", "affiliateId": "7442", "competitorName": "Ramon Soares", "teamCaptain": "0", "gender": "M", "divisionId": "1", "height": "", "regionName": "South America"}, {"status": "ACT", "competitorId": "139866", "countryShortCode": "", "weight": "96 kg", "firstName": "Rodrigo Tannus", "profession": "256", "lastName": "Conceicao", "age": "39", "regionId": "27", "regionalCode": "0", "bibId": "", "profilePicS3key": "f6abd-P139866_3-184.jpg", "scores": [{"score": "12410000", "scoreDisplay": "241 reps"}], "affiliateName": "CrossFit Barra Action", "affiliateId": "8031", "competitorName": "Rodrigo Tannus Conceicao", "teamCaptain": "0", "gender": "M", "divisionId": "18", "height": "180 cm", "regionName": "South America"}, {"status": "ACT", "competitorId": "684425", "countryShortCode": "", "weight": "163 lb", "firstName": "Eduardo", "profession": "0", "lastName": "Terceiro", "age": "26", "regionId": "27", "regionalCode": "0", "bibId": "", "profilePicS3key": "5f82d-P684425_2-184.jpg", "scores": [{"score": "12400000", "scoreDisplay": "240 reps"}], "affiliateName": "CrossFit Jequie", "affiliateId": "7442", "competitorName": "Eduardo Terceiro", "teamCaptain": "0", "gender": "M", "divisionId": "1", "height": "182 cm", "regionName": "South America"}, {"status": "ACT", "competitorId": "752688", "countryShortCode": "", "weight": "85 kg", "firstName": "Tiago", "profession": "32", "lastName": "Amoedo", "age": "38", "regionId": "27", "regionalCode": "0", "bibId": "", "profilePicS3key": "e7934-P752688_1-184.jpg", "scores": [{"score": "12390000", "scoreDisplay": "239 reps"}], "affiliateName": "Pulsar CrossFit", "affiliateId": "11246", "competitorName": "Tiago Amoedo", "teamCaptain": "0", "gender": "M", "divisionId": "18", "height": "186 cm", "regionName": "South America"}, {"status": "ACT", "competitorId": "871396", "countryShortCode": "", "weight": "91 kg", "firstName": "Daniel", "profession": "0", "lastName": "Muneratto", "age": "38", "regionId": "27", "regionalCode": "0", "bibId": "", "profilePicS3key": "8b60f-P871396_1-184.jpg", "scores": [{"score": "12370000", "scoreDisplay": "237 reps"}], "affiliateName": "Pulsar CrossFit", "affiliateId": "11246", "competitorName": "Daniel Muneratto", "teamCaptain": "0", "gender": "M", "divisionId": "18", "height": "182 cm", "regionName": "South America"}, {"status": "ACT", "competitorId": "1218597", "countryShortCode": "", "weight": "71 kg", "firstName": "Mateus", "profession": "128", "lastName": "Bastos Falcao", "age": "26", "regionId": "27", "regionalCode": "0", "bibId": "", "profilePicS3key": "72145-P1218597_1-184.jpg", "scores": [{"score": "12370000", "scoreDisplay": "237 reps"}], "affiliateName": "Aldeia CrossFit", "affiliateId": "10632", "competitorName": "Mateus Bastos Falcao", "teamCaptain": "0", "gender": "M", "divisionId": "1", "height": "169 cm", "regionName": "South America"}, {"status": "ACT", "competitorId": "1396936", "countryShortCode": "", "weight": "", "firstName": "Everton", "profession": "0", "lastName": "Farias", "age": "35", "regionId": "27", "regionalCode": "0", "bibId": "", "profilePicS3key": "pukie.png", "scores": [{"score": "12370000", "scoreDisplay": "237 reps"}], "affiliateName": "Aldeia CrossFit", "affiliateId": "10632", "competitorName": "Everton Farias", "teamCaptain": "0", "gender": "M", "divisionId": "18", "height": "", "regionName": "South America"}, {"status": "ACT", "competitorId": "1219117", "countryShortCode": "", "weight": "85 kg", "firstName": "Alfredo", "profession": "0", "lastName": "Santos Junior", "age": "35", "regionId": "27", "regionalCode": "0", "bibId": "", "profilePicS3key": "3761d-P1219117_1-184.jpg", "scores": [{"score": "12350000", "scoreDisplay": "235 reps"}], "affiliateName": "CrossFit Oxente", "affiliateId": "16767", "competitorName": "Alfredo Santos Junior", "teamCaptain": "0", "gender": "M", "divisionId": "18", "height": "178 cm", "regionName": "South America"}, {"status": "ACT", "competitorId": "1373649", "countryShortCode": "", "weight": "74 kg", "firstName": "Guilherme", "profession": "0", "lastName": "Carneiro da Rocha", "age": "27", "regionId": "27", "regionalCode": "0", "bibId": "", "profilePicS3key": "pukie.png", "scores": [{"score": "12350000", "scoreDisplay": "235 reps"}], "affiliateName": "CrossFit Barra Action", "affiliateId": "8031", "competitorName": "Guilherme Carneiro da Rocha", "teamCaptain": "0", "gender": "M", "divisionId": "1", "height": "183 cm", "regionName": "South America"}, {"status": "ACT", "competitorId": "1365876", "countryShortCode": "", "weight": "92 kg", "firstName": "Gabriel", "profession": "256", "lastName": "Chiaretti", "age": "29", "regionId": "27", "regionalCode": "0", "bibId": "", "profilePicS3key": "b565f-P1365876_1-184.jpg", "scores": [{"score": "12340000", "scoreDisplay": "234 reps"}], "affiliateName": "CrossFit MALTA", "affiliateId": "19903", "competitorName": "Gabriel Chiaretti", "teamCaptain": "0", "gender": "M", "divisionId": "1", "height": "190 cm", "regionName": "South America"}, {"status": "ACT", "competitorId": "807272", "countryShortCode": "", "weight": "73 kg", "firstName": "Wu John", "profession": "0", "lastName": "Ken", "age": "27", "regionId": "27", "regionalCode": "0", "bibId": "", "profilePicS3key": "d32b0-P807272_4-184.jpg", "scores": [{"score": "12340000", "scoreDisplay": "234 reps"}], "affiliateName": "Pulsar CrossFit", "affiliateId": "11246", "competitorName": "Wu John Ken", "teamCaptain": "0", "gender": "M", "divisionId": "1", "height": "", "regionName": "South America"}, {"status": "ACT", "competitorId": "1166721", "countryShortCode": "", "weight": "", "firstName": "Rodolfo", "profession": "256", "lastName": "Azevedo", "age": "31", "regionId": "27", "regionalCode": "0", "bibId": "", "profilePicS3key": "c0f8c-P1166721_1-184.jpg", "scores": [{"score": "12340000", "scoreDisplay": "234 reps"}], "affiliateName": "Aldeia CrossFit", "affiliateId": "10632", "competitorName": "Rodolfo Azevedo", "teamCaptain": "0", "gender": "M", "divisionId": "1", "height": "", "regionName": "South America"}, {"status": "ACT", "competitorId": "1219244", "countryShortCode": "", "weight": "91 kg", "firstName": "Diego", "profession": "0", "lastName": "Ribeiro", "age": "29", "regionId": "27", "regionalCode": "0", "bibId": "", "profilePicS3key": "b21d6-P1219244_1-184.jpg", "scores": [{"score": "12330000", "scoreDisplay": "233 reps"}], "affiliateName": "CrossFit 7373", "affiliateId": "18390", "competitorName": "Diego Ribeiro", "teamCaptain": "0", "gender": "M", "divisionId": "1", "height": "175 cm", "regionName": "South America"}, {"status": "ACT", "competitorId": "612925", "countryShortCode": "", "weight": "71 kg", "firstName": "Fabio", "profession": "0", "lastName": "Pimentel", "age": "33", "regionId": "27", "regionalCode": "0", "bibId": "", "profilePicS3key": "ea679-P612925_1-184.jpg", "scores": [{"score": "12330000", "scoreDisplay": "233 reps"}], "affiliateName": "Aldeia CrossFit", "affiliateId": "10632", "competitorName": "Fabio Pimentel", "teamCaptain": "0", "gender": "M", "divisionId": "1", "height": "170 cm", "regionName": "South America"}, {"status": "ACT", "competitorId": "1092950", "countryShortCode": "", "weight": "90 kg", "firstName": "Luis alberto", "profession": "256", "lastName": "Coelho bahia", "age": "36", "regionId": "27", "regionalCode": "0", "bibId": "", "profilePicS3key": "54742-P1092950_1-184.jpg", "scores": [{"score": "12320000", "scoreDisplay": "232 reps"}], "affiliateName": "CrossFit Alcateia", "affiliateId": "12275", "competitorName": "Luis alberto Coelho bahia", "teamCaptain": "0", "gender": "M", "divisionId": "18", "height": "", "regionName": "South America"}, {"status": "ACT", "competitorId": "1207535", "countryShortCode": "", "weight": "83 kg", "firstName": "Nilson", "profession": "0", "lastName": "Couto", "age": "35", "regionId": "27", "regionalCode": "0", "bibId": "", "profilePicS3key": "pukie.png", "scores": [{"score": "12320000", "scoreDisplay": "232 reps"}], "affiliateName": "Aldeia CrossFit", "affiliateId": "10632", "competitorName": "Nilson Couto", "teamCaptain": "0", "gender": "M", "divisionId": "18", "height": "172 cm", "regionName": "South America"}, {"status": "ACT", "competitorId": "514780", "countryShortCode": "", "weight": "182 lb", "firstName": "Zeca", "profession": "0", "lastName": "Fiori", "age": "23", "regionId": "27", "regionalCode": "0", "bibId": "", "profilePicS3key": "d394d-P514780_1-184.jpg", "scores": [{"score": "12320000", "scoreDisplay": "232 reps"}], "affiliateName": "CrossFit Barra Action", "affiliateId": "8031", "competitorName": "Zeca Fiori", "teamCaptain": "0", "gender": "M", "divisionId": "1", "height": "180 cm", "regionName": "South America"}, {"status": "ACT", "competitorId": "940313", "countryShortCode": "", "weight": "74 kg", "firstName": "Diego", "profession": "1", "lastName": "Souza", "age": "33", "regionId": "27", "regionalCode": "0", "bibId": "", "profilePicS3key": "pukie.png", "scores": [{"score": "12310000", "scoreDisplay": "231 reps"}], "affiliateName": "CrossFit Alcateia", "affiliateId": "12275", "competitorName": "Diego Souza", "teamCaptain": "0", "gender": "M", "divisionId": "1", "height": "170 cm", "regionName": "South America"}, {"status": "ACT", "competitorId": "1159801", "countryShortCode": "", "weight": "74 kg", "firstName": "Daniel", "profession": "2", "lastName": "Macedo", "age": "43", "regionId": "27", "regionalCode": "0", "bibId": "", "profilePicS3key": "pukie.png", "scores": [{"score": "12310000", "scoreDisplay": "231 reps"}], "affiliateName": "Aldeia CrossFit", "affiliateId": "10632", "competitorName": "Daniel Macedo", "teamCaptain": "0", "gender": "M", "divisionId": "12", "height": "173 cm", "regionName": "South America"}, {"status": "ACT", "competitorId": "876406", "countryShortCode": "", "weight": "", "firstName": "Anderson Gabriel", "profession": "128", "lastName": "Souza", "age": "33", "regionId": "27", "regionalCode": "0", "bibId": "", "profilePicS3key": "pukie.png", "scores": [{"score": "12280000", "scoreDisplay": "228 reps"}], "affiliateName": "CrossFit MALTA", "affiliateId": "19903", "competitorName": "Anderson Gabriel Souza", "teamCaptain": "0", "gender": "M", "divisionId": "1", "height": "", "regionName": "South America"}, {"status": "ACT", "competitorId": "761383", "countryShortCode": "", "weight": "110 kg", "firstName": "Bernardo", "profession": "0", "lastName": "Oliveira", "age": "31", "regionId": "27", "regionalCode": "0", "bibId": "", "profilePicS3key": "2ec63-P761383_6-184.jpg", "scores": [{"score": "12280000", "scoreDisplay": "228 reps"}], "affiliateName": "Garagem 164 CrossFit", "affiliateId": "17676", "competitorName": "Bernardo Oliveira", "teamCaptain": "0", "gender": "M", "divisionId": "1", "height": "187 cm", "regionName": "South America"}, {"status": "ACT", "competitorId": "1088596", "countryShortCode": "", "weight": "68 kg", "firstName": "Felipe", "profession": "0", "lastName": "Aragao", "age": "25", "regionId": "27", "regionalCode": "0", "bibId": "", "profilePicS3key": "466bb-P1088596_1-184.jpg", "scores": [{"score": "12280000", "scoreDisplay": "228 reps"}], "affiliateName": "CrossFit Barra Action", "affiliateId": "8031", "competitorName": "Felipe Aragao", "teamCaptain": "0", "gender": "M", "divisionId": "1", "height": "173 cm", "regionName": "South America"}, {"status": "ACT", "competitorId": "1219407", "countryShortCode": "", "weight": "82 kg", "firstName": "Igor", "profession": "0", "lastName": "Chaves", "age": "24", "regionId": "27", "regionalCode": "0", "bibId": "", "profilePicS3key": "749f6-P1219407_3-184.jpg", "scores": [{"score": "12250000", "scoreDisplay": "225 reps"}], "affiliateName": "CrossFit 7373", "affiliateId": "18390", "competitorName": "Igor Chaves", "teamCaptain": "0", "gender": "M", "divisionId": "1", "height": "179 cm", "regionName": "South America"}, {"status": "ACT", "competitorId": "1222352", "countryShortCode": "", "weight": "", "firstName": "Andre", "profession": "0", "lastName": "Serra", "age": "25", "regionId": "27", "regionalCode": "0", "bibId": "", "profilePicS3key": "903b8-P1222352_1-184.jpg", "scores": [{"score": "12250000", "scoreDisplay": "225 reps"}], "affiliateName": "Summer CrossFit", "affiliateId": "15017", "competitorName": "Andre Serra", "teamCaptain": "0", "gender": "M", "divisionId": "1", "height": "", "regionName": "South America"}, {"status": "ACT", "competitorId": "1375862", "countryShortCode": "", "weight": "75 kg", "firstName": "Ytalo", "profession": "0", "lastName": "Rodrigues", "age": "24", "regionId": "27", "regionalCode": "0", "bibId": "", "profilePicS3key": "e728d-P1375862_1-184.jpg", "scores": [{"score": "12240000", "scoreDisplay": "224 reps"}], "affiliateName": "CrossFit MALTA", "affiliateId": "19903", "competitorName": "Ytalo Rodrigues", "teamCaptain": "0", "gender": "M", "divisionId": "1", "height": "175 cm", "regionName": "South America"}, {"status": "ACT", "competitorId": "1322151", "countryShortCode": "", "weight": "", "firstName": "Victor", "profession": "0", "lastName": "Padre Medeiros", "age": "35", "regionId": "27", "regionalCode": "0", "bibId": "", "profilePicS3key": "pukie.png", "scores": [{"score": "12240000", "scoreDisplay": "224 reps"}], "affiliateName": "CrossFit OnzeOnze", "affiliateId": "16711", "competitorName": "Victor Padre Medeiros", "teamCaptain": "0", "gender": "M", "divisionId": "18", "height": "", "regionName": "South America"}, {"status": "ACT", "competitorId": "1205872", "countryShortCode": "", "weight": "74 kg", "firstName": "Anderson", "profession": "256", "lastName": "Barnabe", "age": "39", "regionId": "27", "regionalCode": "0", "bibId": "", "profilePicS3key": "0def3-P1205872_1-184.jpg", "scores": [{"score": "12240000", "scoreDisplay": "224 reps"}], "affiliateName": "Pulsar CrossFit", "affiliateId": "11246", "competitorName": "Anderson Barnabe", "teamCaptain": "0", "gender": "M", "divisionId": "18", "height": "179 cm", "regionName": "South America"}, {"status": "ACT", "competitorId": "1252773", "countryShortCode": "", "weight": "", "firstName": "Luiz Gustavo", "profession": "128", "lastName": "Rodrigues Teixeira", "age": "40", "regionId": "27", "regionalCode": "0", "bibId": "", "profilePicS3key": "01a2f-P1252773_3-184.jpg", "scores": [{"score": "12240000", "scoreDisplay": "224 reps"}], "affiliateName": "Aldeia CrossFit", "affiliateId": "10632", "competitorName": "Luiz Gustavo Rodrigues Teixeira", "teamCaptain": "0", "gender": "M", "divisionId": "12", "height": "", "regionName": "South America"}, {"status": "ACT", "competitorId": "861760", "countryShortCode": "", "weight": "", "firstName": "Italo", "profession": "0", "lastName": "Brandao", "age": "30", "regionId": "27", "regionalCode": "0", "bibId": "", "profilePicS3key": "pukie.png", "scores": [{"score": "12240000", "scoreDisplay": "224 reps"}], "affiliateName": "Aldeia CrossFit", "affiliateId": "10632", "competitorName": "Italo Brandao", "teamCaptain": "0", "gender": "M", "divisionId": "1", "height": "", "regionName": "South America"}, {"status": "ACT", "competitorId": "945504", "countryShortCode": "", "weight": "68 kg", "firstName": "Marcos", "profession": "256", "lastName": "William", "age": "31", "regionId": "27", "regionalCode": "0", "bibId": "", "profilePicS3key": "pukie.png", "scores": [{"score": "12230000", "scoreDisplay": "223 reps"}], "affiliateName": "CrossFit MALTA", "affiliateId": "19903", "competitorName": "Marcos William", "teamCaptain": "0", "gender": "M", "divisionId": "1", "height": "165 cm", "regionName": "South America"}, {"status": "ACT", "competitorId": "1248636", "countryShortCode": "", "weight": "", "firstName": "Alberto", "profession": "0", "lastName": "Nunes", "age": "28", "regionId": "27", "regionalCode": "0", "bibId": "", "profilePicS3key": "pukie.png", "scores": [{"score": "12210000", "scoreDisplay": "221 reps"}], "affiliateName": "Pulsar CrossFit", "affiliateId": "11246", "competitorName": "Alberto Nunes", "teamCaptain": "0", "gender": "M", "divisionId": "1", "height": "", "regionName": "South America"}, {"status": "ACT", "competitorId": "1252177", "countryShortCode": "", "weight": "", "firstName": "Marcelo", "profession": "0", "lastName": "Kruschewsky", "age": "35", "regionId": "27", "regionalCode": "0", "bibId": "", "profilePicS3key": "pukie.png", "scores": [{"score": "12200000", "scoreDisplay": "220 reps"}], "affiliateName": "CrossFit Alcateia", "affiliateId": "12275", "competitorName": "Marcelo Kruschewsky", "teamCaptain": "0", "gender": "M", "divisionId": "18", "height": "", "regionName": "South America"}, {"status": "ACT", "competitorId": "1339065", "countryShortCode": "", "weight": "88 kg", "firstName": "Marco Antonio", "profession": "256", "lastName": "Peres", "age": "36", "regionId": "27", "regionalCode": "0", "bibId": "", "profilePicS3key": "ba9c5-P1339065_1-184.jpg", "scores": [{"score": "12180000", "scoreDisplay": "218 reps"}], "affiliateName": "CrossFit 7373", "affiliateId": "18390", "competitorName": "Marco Antonio Peres", "teamCaptain": "0", "gender": "M", "divisionId": "18", "height": "", "regionName": "South America"}, {"status": "ACT", "competitorId": "1062507", "countryShortCode": "", "weight": "72 kg", "firstName": "Victor", "profession": "0", "lastName": "Campelo", "age": "29", "regionId": "27", "regionalCode": "0", "bibId": "", "profilePicS3key": "b2acf-P1062507_1-184.jpg", "scores": [{"score": "12160000", "scoreDisplay": "216 reps"}], "affiliateName": "CrossFit Alcateia", "affiliateId": "12275", "competitorName": "Victor Campelo", "teamCaptain": "0", "gender": "M", "divisionId": "1", "height": "168 cm", "regionName": "South America"}, {"status": "ACT", "competitorId": "1393557", "countryShortCode": "", "weight": "", "firstName": "Francisco", "profession": "0", "lastName": "Neto", "age": "23", "regionId": "27", "regionalCode": "0", "bibId": "", "profilePicS3key": "pukie.png", "scores": [{"score": "12150000", "scoreDisplay": "215 reps"}], "affiliateName": "Pulsar CrossFit", "affiliateId": "11246", "competitorName": "Francisco Neto", "teamCaptain": "0", "gender": "M", "divisionId": "1", "height": "", "regionName": "South America"}, {"status": "ACT", "competitorId": "1362235", "countryShortCode": "", "weight": "78 kg", "firstName": "Felipe", "profession": "128", "lastName": "Ribeiro", "age": "25", "regionId": "27", "regionalCode": "0", "bibId": "", "profilePicS3key": "pukie.png", "scores": [{"score": "12140000", "scoreDisplay": "214 reps"}], "affiliateName": "CrossFit Alcateia", "affiliateId": "12275", "competitorName": "Felipe Ribeiro", "teamCaptain": "0", "gender": "M", "divisionId": "1", "height": "", "regionName": "South America"}, {"status": "ACT", "competitorId": "1369750", "countryShortCode": "", "weight": "75 kg", "firstName": "Igor", "profession": "1", "lastName": "Lima", "age": "26", "regionId": "27", "regionalCode": "0", "bibId": "", "profilePicS3key": "8a898-P1369750_1-184.jpg", "scores": [{"score": "12130000", "scoreDisplay": "213 reps"}], "affiliateName": "CrossFit MALTA", "affiliateId": "19903", "competitorName": "Igor Lima", "teamCaptain": "0", "gender": "M", "divisionId": "1", "height": "", "regionName": "South America"}, {"status": "ACT", "competitorId": "1322949", "countryShortCode": "", "weight": "81 kg", "firstName": "Hugo", "profession": "16", "lastName": "Madera", "age": "30", "regionId": "27", "regionalCode": "0", "bibId": "", "profilePicS3key": "badac-P1322949_1-184.jpg", "scores": [{"score": "12100000", "scoreDisplay": "210 reps"}], "affiliateName": "CrossFit MALTA", "affiliateId": "19903", "competitorName": "Hugo Madera", "teamCaptain": "0", "gender": "M", "divisionId": "1", "height": "", "regionName": "South America"}, {"status": "ACT", "competitorId": "1333642", "countryShortCode": "", "weight": "", "firstName": "Daniel", "profession": "0", "lastName": "Del Rei", "age": "37", "regionId": "27", "regionalCode": "0", "bibId": "", "profilePicS3key": "0aff1-P1333642_1-184.jpg", "scores": [{"score": "12100000", "scoreDisplay": "210 reps"}], "affiliateName": "CrossFit 7373", "affiliateId": "18390", "competitorName": "Daniel Del Rei", "teamCaptain": "0", "gender": "M", "divisionId": "18", "height": "", "regionName": "South America"}, {"status": "ACT", "competitorId": "1323876", "countryShortCode": "", "weight": "84 kg", "firstName": "Alexandre", "profession": "256", "lastName": "Santos", "age": "34", "regionId": "27", "regionalCode": "0", "bibId": "", "profilePicS3key": "b4fe3-P1323876_1-184.jpg", "scores": [{"score": "12100000", "scoreDisplay": "210 reps"}], "affiliateName": "CrossFit OnzeOnze", "affiliateId": "16711", "competitorName": "Alexandre Santos", "teamCaptain": "0", "gender": "M", "divisionId": "1", "height": "178 cm", "regionName": "South America"}, {"status": "ACT", "competitorId": "986911", "countryShortCode": "", "weight": "71 kg", "firstName": "Paulo", "profession": "256", "lastName": "Fernandes", "age": "24", "regionId": "27", "regionalCode": "0", "bibId": "", "profilePicS3key": "55457-P986911_1-184.jpg", "scores": [{"score": "12100000", "scoreDisplay": "210 reps"}], "affiliateName": "CrossFit Alcateia", "affiliateId": "12275", "competitorName": "Paulo Fernandes", "teamCaptain": "0", "gender": "M", "divisionId": "1", "height": "", "regionName": "South America"}, {"status": "ACT", "competitorId": "752891", "countryShortCode": "", "weight": "68 kg", "firstName": "Ricardo", "profession": "0", "lastName": "Simoes", "age": "30", "regionId": "27", "regionalCode": "0", "bibId": "", "profilePicS3key": "pukie.png", "scores": [{"score": "12100000", "scoreDisplay": "210 reps"}], "affiliateName": "Pulsar CrossFit", "affiliateId": "11246", "competitorName": "Ricardo Simoes", "teamCaptain": "0", "gender": "M", "divisionId": "1", "height": "2 cm", "regionName": "South America"}, {"status": "ACT", "competitorId": "722084", "countryShortCode": "", "weight": "", "firstName": "Tiago", "profession": "0", "lastName": "Marmund", "age": "26", "regionId": "27", "regionalCode": "0", "bibId": "", "profilePicS3key": "pukie.png", "scores": [{"score": "12080000", "scoreDisplay": "208 reps"}], "affiliateName": "CrossFit Barra Action", "affiliateId": "8031", "competitorName": "Tiago Marmund", "teamCaptain": "0", "gender": "M", "divisionId": "1", "height": "", "regionName": "South America"}, {"status": "ACT", "competitorId": "1397635", "countryShortCode": "", "weight": "85 kg", "firstName": "Leonardo", "profession": "2", "lastName": "Louren\u00e7o", "age": "41", "regionId": "27", "regionalCode": "0", "bibId": "", "profilePicS3key": "9f0b4-P1397635_1-184.jpg", "scores": [{"score": "12050000", "scoreDisplay": "205 reps"}], "affiliateName": "CrossFit Alcateia", "affiliateId": "12275", "competitorName": "Leonardo Louren\u00e7o", "teamCaptain": "0", "gender": "M", "divisionId": "12", "height": "", "regionName": "South America"}, {"status": "ACT", "competitorId": "576124", "countryShortCode": "", "weight": "77 kg", "firstName": "Joao Paulo", "profession": "0", "lastName": "Canario", "age": "32", "regionId": "27", "regionalCode": "0", "bibId": "", "profilePicS3key": "ab613-P576124_2-184.jpg", "scores": [{"score": "12040000", "scoreDisplay": "204 reps"}], "affiliateName": "CrossFit Barra Action", "affiliateId": "8031", "competitorName": "Joao Paulo Canario", "teamCaptain": "0", "gender": "M", "divisionId": "1", "height": "167 cm", "regionName": "South America"}, {"status": "ACT", "competitorId": "1215374", "countryShortCode": "", "weight": "84 kg", "firstName": "R\u00f4mulo", "profession": "128", "lastName": "Silva", "age": "24", "regionId": "27", "regionalCode": "0", "bibId": "", "profilePicS3key": "2272f-P1215374_2-184.jpg", "scores": [{"score": "11950000", "scoreDisplay": "195 reps"}], "affiliateName": "CrossFit 7373", "affiliateId": "18390", "competitorName": "R\u00f4mulo Silva", "teamCaptain": "0", "gender": "M", "divisionId": "1", "height": "184 cm", "regionName": "South America"}, {"status": "ACT", "competitorId": "1380568", "countryShortCode": "", "weight": "", "firstName": "Altemar", "profession": "0", "lastName": "Silva", "age": "29", "regionId": "27", "regionalCode": "0", "bibId": "", "profilePicS3key": "pukie.png", "scores": [{"score": "11940000", "scoreDisplay": "194 reps"}], "affiliateName": "Pulsar CrossFit", "affiliateId": "11246", "competitorName": "Altemar Silva", "teamCaptain": "0", "gender": "M", "divisionId": "1", "height": "", "regionName": "South America"}, {"status": "ACT", "competitorId": "1241278", "countryShortCode": "", "weight": "70 kg", "firstName": "Rodrigo", "profession": "0", "lastName": "Araujo Craveiro", "age": "33", "regionId": "27", "regionalCode": "0", "bibId": "", "profilePicS3key": "5f36e-P1241278_1-184.jpg", "scores": [{"score": "11920000", "scoreDisplay": "192 reps"}], "affiliateName": "CrossFit MALTA", "affiliateId": "19903", "competitorName": "Rodrigo Araujo Craveiro", "teamCaptain": "0", "gender": "M", "divisionId": "1", "height": "173 cm", "regionName": "South America"}, {"status": "ACT", "competitorId": "923110", "countryShortCode": "", "weight": "", "firstName": "Pedro", "profession": "128", "lastName": "Brito", "age": "20", "regionId": "27", "regionalCode": "0", "bibId": "", "profilePicS3key": "pukie.png", "scores": [{"score": "11920000", "scoreDisplay": "192 reps"}], "affiliateName": "Summer CrossFit", "affiliateId": "15017", "competitorName": "Pedro Brito", "teamCaptain": "0", "gender": "M", "divisionId": "1", "height": "", "regionName": "South America"}, {"status": "ACT", "competitorId": "1395206", "countryShortCode": "", "weight": "", "firstName": "Wal", "profession": "0", "lastName": "Junior", "age": "31", "regionId": "27", "regionalCode": "0", "bibId": "", "profilePicS3key": "pukie.png", "scores": [{"score": "11810000", "scoreDisplay": "181 reps"}], "affiliateName": "CrossFit Alcateia", "affiliateId": "12275", "competitorName": "Wal Junior", "teamCaptain": "0", "gender": "M", "divisionId": "1", "height": "", "regionName": "South America"}, {"status": "ACT", "competitorId": "1324406", "countryShortCode": "", "weight": "68 kg", "firstName": "Pedro", "profession": "161", "lastName": "Santos", "age": "36", "regionId": "27", "regionalCode": "0", "bibId": "", "profilePicS3key": "10ae6-P1324406_1-184.jpg", "scores": [{"score": "11780000", "scoreDisplay": "178 reps"}], "affiliateName": "CrossFit Oxente", "affiliateId": "16767", "competitorName": "Pedro Santos", "teamCaptain": "0", "gender": "M", "divisionId": "18", "height": "166 cm", "regionName": "South America"}, {"status": "ACT", "competitorId": "683173", "countryShortCode": "", "weight": "75 kg", "firstName": "Rosalvo", "profession": "256", "lastName": "Neto", "age": "41", "regionId": "27", "regionalCode": "0", "bibId": "", "profilePicS3key": "2dd50-P683173_2-184.jpg", "scores": [{"score": "11750000", "scoreDisplay": "175 reps"}], "affiliateName": "CrossFit SSA", "affiliateId": "13482", "competitorName": "Rosalvo Neto", "teamCaptain": "0", "gender": "M", "divisionId": "12", "height": "175 cm", "regionName": "South America"}, {"status": "ACT", "competitorId": "1007142", "countryShortCode": "", "weight": "", "firstName": "Gabriel", "profession": "0", "lastName": "Ribeiro", "age": "33", "regionId": "27", "regionalCode": "0", "bibId": "", "profilePicS3key": "pukie.png", "scores": [{"score": "11670000", "scoreDisplay": "167 reps"}], "affiliateName": "Pulsar CrossFit", "affiliateId": "11246", "competitorName": "Gabriel Ribeiro", "teamCaptain": "0", "gender": "M", "divisionId": "1", "height": "", "regionName": "South America"}, {"status": "ACT", "competitorId": "1393506", "countryShortCode": "", "weight": "", "firstName": "Rafael", "profession": "0", "lastName": "Vasconcelos", "age": "29", "regionId": "27", "regionalCode": "0", "bibId": "", "profilePicS3key": "pukie.png", "scores": [{"score": "11620000", "scoreDisplay": "162 reps"}], "affiliateName": "Go Piat\u00e3 CrossFit", "affiliateId": "20153", "competitorName": "Rafael Vasconcelos", "teamCaptain": "0", "gender": "M", "divisionId": "1", "height": "", "regionName": "South America"}, {"status": "ACT", "competitorId": "1248252", "countryShortCode": "", "weight": "", "firstName": "Rodrigo de jesus", "profession": "0", "lastName": "Pinheiro", "age": "24", "regionId": "27", "regionalCode": "0", "bibId": "", "profilePicS3key": "40e3a-P1248252_1-184.jpg", "scores": [{"score": "11610000", "scoreDisplay": "161 reps"}], "affiliateName": "CrossFit 7373", "affiliateId": "18390", "competitorName": "Rodrigo de jesus Pinheiro", "teamCaptain": "0", "gender": "M", "divisionId": "1", "height": "", "regionName": "South America"}, {"status": "ACT", "competitorId": "1270026", "countryShortCode": "", "weight": "92 kg", "firstName": "Roberto", "profession": "128", "lastName": "Meirelles", "age": "39", "regionId": "27", "regionalCode": "0", "bibId": "", "profilePicS3key": "8616b-P1270026_1-184.jpg", "scores": [{"score": "11280000", "scoreDisplay": "128 reps"}], "affiliateName": "CrossFit Alcateia", "affiliateId": "12275", "competitorName": "Roberto Meirelles", "teamCaptain": "0", "gender": "M", "divisionId": "18", "height": "183 cm", "regionName": "South America"}, {"status": "ACT", "competitorId": "1314821", "countryShortCode": "", "weight": "", "firstName": "Danilo", "profession": "0", "lastName": "Ribeiro", "age": "38", "regionId": "27", "regionalCode": "0", "bibId": "", "profilePicS3key": "pukie.png", "scores": [{"score": "0", "scoreDisplay": ""}], "affiliateName": "CrossFit MALTA", "affiliateId": "19903", "competitorName": "Danilo Ribeiro", "teamCaptain": "0", "gender": "M", "divisionId": "18", "height": "", "regionName": "South America"}, {"status": "ACT", "competitorId": "747276", "countryShortCode": "", "weight": "89 kg", "firstName": "Livio", "profession": "0", "lastName": "Silva", "age": "25", "regionId": "27", "regionalCode": "0", "bibId": "", "profilePicS3key": "4ece4-P747276_3-184.jpg", "scores": [{"score": "0", "scoreDisplay": ""}], "affiliateName": "CrossFit MALTA", "affiliateId": "19903", "competitorName": "Livio Silva", "teamCaptain": "0", "gender": "M", "divisionId": "1", "height": "171 cm", "regionName": "South America"}, {"status": "ACT", "competitorId": "818667", "countryShortCode": "", "weight": "82 kg", "firstName": "Lucas", "profession": "0", "lastName": "Pitta", "age": "31", "regionId": "27", "regionalCode": "0", "bibId": "", "profilePicS3key": "08ce8-P818667_1-184.jpg", "scores": [{"score": "0", "scoreDisplay": ""}], "affiliateName": "CrossFit MALTA", "affiliateId": "19903", "competitorName": "Lucas Pitta", "teamCaptain": "0", "gender": "M", "divisionId": "1", "height": "180 cm", "regionName": "South America"}, {"status": "ACT", "competitorId": "1258501", "countryShortCode": "", "weight": "68 kg", "firstName": "Bruno", "profession": "0", "lastName": "Carvalho Ferreira", "age": "30", "regionId": "27", "regionalCode": "0", "bibId": "", "profilePicS3key": "b3bed-P1258501_2-184.jpg", "scores": [{"score": "0", "scoreDisplay": ""}], "affiliateName": "CrossFit Itabuna", "affiliateId": "18910", "competitorName": "Bruno Carvalho Ferreira", "teamCaptain": "0", "gender": "M", "divisionId": "1", "height": "1700 cm", "regionName": "South America"}, {"status": "ACT", "competitorId": "1241724", "countryShortCode": "", "weight": "71 kg", "firstName": "Samir", "profession": "0", "lastName": "Silva", "age": "20", "regionId": "27", "regionalCode": "0", "bibId": "", "profilePicS3key": "2195e-P1241724_1-184.jpg", "scores": [{"score": "0", "scoreDisplay": ""}], "affiliateName": "CrossFit Itabuna", "affiliateId": "18910", "competitorName": "Samir Silva", "teamCaptain": "0", "gender": "M", "divisionId": "1", "height": "", "regionName": "South America"}, {"status": "ACT", "competitorId": "542512", "countryShortCode": "", "weight": "91 kg", "firstName": "Tasso", "profession": "96", "lastName": "Souza", "age": "36", "regionId": "27", "regionalCode": "0", "bibId": "", "profilePicS3key": "8b5eb-P542512_3-184.jpg", "scores": [{"score": "0", "scoreDisplay": ""}], "affiliateName": "CrossFit 7373", "affiliateId": "18390", "competitorName": "Tasso Souza", "teamCaptain": "0", "gender": "M", "divisionId": "18", "height": "", "regionName": "South America"}, {"status": "ACT", "competitorId": "1409699", "countryShortCode": "", "weight": "", "firstName": "Anderson", "profession": "0", "lastName": "Vicente", "age": "36", "regionId": "27", "regionalCode": "0", "bibId": "", "profilePicS3key": "pukie.png", "scores": [{"score": "0", "scoreDisplay": ""}], "affiliateName": "CrossFit OnzeOnze", "affiliateId": "16711", "competitorName": "Anderson Vicente", "teamCaptain": "0", "gender": "M", "divisionId": "18", "height": "", "regionName": "South America"}, {"status": "ACT", "competitorId": "1411354", "countryShortCode": "", "weight": "", "firstName": "Ramon", "profession": "0", "lastName": "Andrade", "age": "26", "regionId": "27", "regionalCode": "0", "bibId": "", "profilePicS3key": "pukie.png", "scores": [{"score": "0", "scoreDisplay": ""}], "affiliateName": "CrossFit OnzeOnze", "affiliateId": "16711", "competitorName": "Ramon Andrade", "teamCaptain": "0", "gender": "M", "divisionId": "1", "height": "", "regionName": "South America"}, {"status": "ACT", "competitorId": "1107336", "countryShortCode": "", "weight": "73 kg", "firstName": "Lucas", "profession": "128", "lastName": "Aranchipe", "age": "20", "regionId": "27", "regionalCode": "0", "bibId": "", "profilePicS3key": "pukie.png", "scores": [{"score": "0", "scoreDisplay": ""}], "affiliateName": "CrossFit Maral", "affiliateId": "16225", "competitorName": "Lucas Aranchipe", "teamCaptain": "0", "gender": "M", "divisionId": "1", "height": "173 cm", "regionName": "South America"}, {"status": "ACT", "competitorId": "480612", "countryShortCode": "", "weight": "174 lb", "firstName": "Lucas", "profession": "0", "lastName": "Oliveira", "age": "23", "regionId": "27", "regionalCode": "0", "bibId": "", "profilePicS3key": "pukie.png", "scores": [{"score": "0", "scoreDisplay": ""}], "affiliateName": "Summer CrossFit", "affiliateId": "15017", "competitorName": "Lucas Oliveira", "teamCaptain": "0", "gender": "M", "divisionId": "1", "height": "174 cm", "regionName": "South America"}, {"status": "ACT", "competitorId": "1396271", "countryShortCode": "", "weight": "", "firstName": "Thiago", "profession": "0", "lastName": "Aquino", "age": "36", "regionId": "27", "regionalCode": "0", "bibId": "", "profilePicS3key": "pukie.png", "scores": [{"score": "0", "scoreDisplay": ""}], "affiliateName": "CrossFit Alcateia", "affiliateId": "12275", "competitorName": "Thiago Aquino", "teamCaptain": "0", "gender": "M", "divisionId": "18", "height": "", "regionName": "South America"}, {"status": "ACT", "competitorId": "1349966", "countryShortCode": "", "weight": "", "firstName": "Enrico", "profession": "0", "lastName": "Mattei", "age": "32", "regionId": "27", "regionalCode": "0", "bibId": "", "profilePicS3key": "pukie.png", "scores": [{"score": "0", "scoreDisplay": ""}], "affiliateName": "Aldeia CrossFit", "affiliateId": "10632", "competitorName": "Enrico Mattei", "teamCaptain": "0", "gender": "M", "divisionId": "1", "height": "", "regionName": "South America"}, {"status": "ACT", "competitorId": "773234", "countryShortCode": "", "weight": "76 kg", "firstName": "Carlos", "profession": "0", "lastName": "Oliveira J\u00fanior", "age": "53", "regionId": "27", "regionalCode": "0", "bibId": "", "profilePicS3key": "f7b4b-P773234_8-184.jpg", "scores": [{"score": "0", "scoreDisplay": ""}], "affiliateName": "Aldeia CrossFit", "affiliateId": "10632", "competitorName": "Carlos Oliveira J\u00fanior", "teamCaptain": "0", "gender": "M", "divisionId": "5", "height": "176 cm", "regionName": "South America"}, {"status": "ACT", "competitorId": "1370487", "countryShortCode": "", "weight": "", "firstName": "Fabio", "profession": "0", "lastName": "Santos", "age": "33", "regionId": "27", "regionalCode": "0", "bibId": "", "profilePicS3key": "pukie.png", "scores": [{"score": "0", "scoreDisplay": ""}], "affiliateName": "Aldeia CrossFit", "affiliateId": "10632", "competitorName": "Fabio Santos", "teamCaptain": "0", "gender": "M", "divisionId": "1", "height": "", "regionName": "South America"}, {"status": "ACT", "competitorId": "795545", "countryShortCode": "", "weight": "", "firstName": "Rodrigo", "profession": "0", "lastName": "Amaral", "age": "27", "regionId": "27", "regionalCode": "0", "bibId": "", "profilePicS3key": "pukie.png", "scores": [{"score": "0", "scoreDisplay": ""}], "affiliateName": "CrossFit Barra Action", "affiliateId": "8031", "competitorName": "Rodrigo Amaral", "teamCaptain": "0", "gender": "M", "divisionId": "1", "height": "", "regionName": "South America"}]